Workbook

Sheet Main
A1: Name (DisplayName) | B1: Contact Number | C1: Zone | D1: Connection | E1: Location | F1: Info | G1: Info_Date | H1: Invite | I1: Invite_Date | J1: Plan | K1: Comments | L1: Notes
A2: Samsung Helpline | B2: 1800407267864 | F2: =IFERROR(LOOKUP(2,1/('Weekly Tracker'!$E$2:$E$766=$A2)/('Weekly Tracker'!$F$2:$F$766<>""),'Weekly Tracker'!$F$2:$F$766),"") | G2: =IF(F2<>"",LOOKUP(2,1/('Weekly Tracker'!$E$2:$E$766=$A2)/('Weekly Tracker'!$F$2:$F$766<>""),'Weekly Tracker'!$G$2:$G$766),"") | H2: =IFERROR(LOOKUP(2,1/('Weekly Tracker'!$E$2:$E$766=$A2)/('Weekly Tracker'!$H$2:$H$766<>""),'Weekly Tracker'!$H$2:$H$766),"") | I2: =IF(H2<>"",LOOKUP(2,1/('Weekly Tracker'!$E$2:$E$766=$A2)/('Weekly Tracker'!$H$2:$H$766<>""),'Weekly Tracker'!$I$2:$I$766),"") | J2: =IFERROR(LOOKUP(2,1/('Weekly Tracker'!$E$2:$E$766=$A2)/('Weekly Tracker'!$J$2:$J$766<>""),'Weekly Tracker'!$J$2:$J$766),"") | K2: =IFERROR(LOOKUP(2,1/('Weekly Tracker'!$E$2:$E$766=$A2)/('Weekly Tracker'!$N$2:$N$766<>""),'Weekly Tracker'!$N$2:$N$766),"") | L2: =IFERROR(LOOKUP(2,1/('Weekly Tracker'!$E$2:$E$766=$A2)/('Weekly Tracker'!$O$2:$O$766<>""),'Weekly Tracker'!$O$2:$O$766),"")
A3: Ragul Urja | B3: 917806971707, +91 78069 71707 | F3: =IFERROR(LOOKUP(2,1/('Weekly Tracker'!$E$2:$E$766=$A3)/('Weekly Tracker'!$F$2:$F$766<>""),'Weekly Tracker'!$F$2:$F$766),"") | G3: =IF(F3<>"",LOOKUP(2,1/('Weekly Tracker'!$E$2:$E$766=$A3)/('Weekly Tracker'!$F$2:$F$766<>""),'Weekly Tracker'!$G$2:$G$766),"") | H3: =IFERROR(LOOKUP(2,1/('Weekly Tracker'!$E$2:$E$766=$A3)/('Weekly Tracker'!$H$2:$H$766<>""),'Weekly Tracker'!$H$2:$H$766),"") | I3: =IF(H3<>"",LOOKUP(2,1/('Weekly Tracker'!$E$2:$E$766=$A3)/('Weekly Tracker'!$H$2:$H$766<>""),'Weekly Tracker'!$I$2:$I$766),"") | J3: =IFERROR(LOOKUP(2,1/('Weekly Tracker'!$E$2:$E$766=$A3)/('Weekly Tracker'!$J$2:$J$766<>""),'Weekly Tracker'!$J$2:$J$766),"") | K3: =IFERROR(LOOKUP(2,1/('Weekly Tracker'!$E$2:$E$766=$A3)/('Weekly Tracker'!$N$2:$N$766<>""),'Weekly Tracker'!$N$2:$N$766),"") | L3: =IFERROR(LOOKUP(2,1/('Weekly Tracker'!$E$2:$E$766=$A3)/('Weekly Tracker'!$O$2:$O$766<>""),'Weekly Tracker'!$O$2:$O$766),"")
A4: Rajesh ramadoss Urja | B4: 919952925095 | F4: =IFERROR(LOOKUP(2,1/('Weekly Tracker'!$E$2:$E$766=$A4)/('Weekly Tracker'!$F$2:$F$766<>""),'Weekly Tracker'!$F$2:$F$766),"") | G4: =IF(F4<>"",LOOKUP(2,1/('Weekly Tracker'!$E$2:$E$766=$A4)/('Weekly Tracker'!$F$2:$F$766<>""),'Weekly Tracker'!$G$2:$G$766),"") | H4: =IFERROR(LOOKUP(2,1/('Weekly Tracker'!$E$2:$E$766=$A4)/('Weekly Tracker'!$H$2:$H$766<>""),'Weekly Tracker'!$H$2:$H$766),"") | I4: =IF(H4<>"",LOOKUP(2,1/('Weekly Tracker'!$E$2:$E$766=$A4)/('Weekly Tracker'!$H$2:$H$766<>""),'Weekly Tracker'!$I$2:$I$766),"") | J4: =IFERROR(LOOKUP(2,1/('Weekly Tracker'!$E$2:$E$766=$A4)/('Weekly Tracker'!$J$2:$J$766<>""),'Weekly Tracker'!$J$2:$J$766),"") | K4: =IFERROR(LOOKUP(2,1/('Weekly Tracker'!$E$2:$E$766=$A4)/('Weekly Tracker'!$N$2:$N$766<>""),'Weekly Tracker'!$N$2:$N$766),"") | L4: =IFERROR(LOOKUP(2,1/('Weekly Tracker'!$E$2:$E$766=$A4)/('Weekly Tracker'!$O$2:$O$766<>""),'Weekly Tracker'!$O$2:$O$766),"")
A5: Rajesh Past Urja | B5: 919790921712 | F5: =IFERROR(LOOKUP(2,1/('Weekly Tracker'!$E$2:$E$766=$A5)/('Weekly Tracker'!$F$2:$F$766<>""),'Weekly Tracker'!$F$2:$F$766),"") | G5: =IF(F5<>"",LOOKUP(2,1/('Weekly Tracker'!$E$2:$E$766=$A5)/('Weekly Tracker'!$F$2:$F$766<>""),'Weekly Tracker'!$G$2:$G$766),"") | H5: =IFERROR(LOOKUP(2,1/('Weekly Tracker'!$E$2:$E$766=$A5)/('Weekly Tracker'!$H$2:$H$766<>""),'Weekly Tracker'!$H$2:$H$766),"") | I5: =IF(H5<>"",LOOKUP(2,1/('Weekly Tracker'!$E$2:$E$766=$A5)/('Weekly Tracker'!$H$2:$H$766<>""),'Weekly Tracker'!$I$2:$I$766),"") | J5: =IFERROR(LOOKUP(2,1/('Weekly Tracker'!$E$2:$E$766=$A5)/('Weekly Tracker'!$J$2:$J$766<>""),'Weekly Tracker'!$J$2:$J$766),"") | K5: =IFERROR(LOOKUP(2,1/('Weekly Tracker'!$E$2:$E$766=$A5)/('Weekly Tracker'!$N$2:$N$766<>""),'Weekly Tracker'!$N$2:$N$766),"") | L5: =IFERROR(LOOKUP(2,1/('Weekly Tracker'!$E$2:$E$766=$A5)/('Weekly Tracker'!$O$2:$O$766<>""),'Weekly Tracker'!$O$2:$O$766),"")
A6: Ragul Hit Urja | B6: 919944401970 | F6: =IFERROR(LOOKUP(2,1/('Weekly Tracker'!$E$2:$E$766=$A6)/('Weekly Tracker'!$F$2:$F$766<>""),'Weekly Tracker'!$F$2:$F$766),"") | G6: =IF(F6<>"",LOOKUP(2,1/('Weekly Tracker'!$E$2:$E$766=$A6)/('Weekly Tracker'!$F$2:$F$766<>""),'Weekly Tracker'!$G$2:$G$766),"") | H6: =IFERROR(LOOKUP(2,1/('Weekly Tracker'!$E$2:$E$766=$A6)/('Weekly Tracker'!$H$2:$H$766<>""),'Weekly Tracker'!$H$2:$H$766),"") | I6: =IF(H6<>"",LOOKUP(2,1/('Weekly Tracker'!$E$2:$E$766=$A6)/('Weekly Tracker'!$H$2:$H$766<>""),'Weekly Tracker'!$I$2:$I$766),"") | J6: =IFERROR(LOOKUP(2,1/('Weekly Tracker'!$E$2:$E$766=$A6)/('Weekly Tracker'!$J$2:$J$766<>""),'Weekly Tracker'!$J$2:$J$766),"") | K6: =IFERROR(LOOKUP(2,1/('Weekly Tracker'!$E$2:$E$766=$A6)/('Weekly Tracker'!$N$2:$N$766<>""),'Weekly Tracker'!$N$2:$N$766),"") | L6: =IFERROR(LOOKUP(2,1/('Weekly Tracker'!$E$2:$E$766=$A6)/('Weekly Tracker'!$O$2:$O$766<>""),'Weekly Tracker'!$O$2:$O$766),"")
A7: Rajesh FB | B7: 8428885607, 84288 85607 | F7: =IFERROR(LOOKUP(2,1/('Weekly Tracker'!$E$2:$E$766=$A7)/('Weekly Tracker'!$F$2:$F$766<>""),'Weekly Tracker'!$F$2:$F$766),"") | G7: =IF(F7<>"",LOOKUP(2,1/('Weekly Tracker'!$E$2:$E$766=$A7)/('Weekly Tracker'!$F$2:$F$766<>""),'Weekly Tracker'!$G$2:$G$766),"") | H7: =IFERROR(LOOKUP(2,1/('Weekly Tracker'!$E$2:$E$766=$A7)/('Weekly Tracker'!$H$2:$H$766<>""),'Weekly Tracker'!$H$2:$H$766),"") | I7: =IF(H7<>"",LOOKUP(2,1/('Weekly Tracker'!$E$2:$E$766=$A7)/('Weekly Tracker'!$H$2:$H$766<>""),'Weekly Tracker'!$I$2:$I$766),"") | J7: =IFERROR(LOOKUP(2,1/('Weekly Tracker'!$E$2:$E$766=$A7)/('Weekly Tracker'!$J$2:$J$766<>""),'Weekly Tracker'!$J$2:$J$766),"") | K7: =IFERROR(LOOKUP(2,1/('Weekly Tracker'!$E$2:$E$766=$A7)/('Weekly Tracker'!$N$2:$N$766<>""),'Weekly Tracker'!$N$2:$N$766),"") | L7: =IFERROR(LOOKUP(2,1/('Weekly Tracker'!$E$2:$E$766=$A7)/('Weekly Tracker'!$O$2:$O$766<>""),'Weekly Tracker'!$O$2:$O$766),"")
A8: Rakesh Urja | B8: 919551130445, +91 95511 30445 | F8: =IFERROR(LOOKUP(2,1/('Weekly Tracker'!$E$2:$E$766=$A8)/('Weekly Tracker'!$F$2:$F$766<>""),'Weekly Tracker'!$F$2:$F$766),"") | G8: =IF(F8<>"",LOOKUP(2,1/('Weekly Tracker'!$E$2:$E$766=$A8)/('Weekly Tracker'!$F$2:$F$766<>""),'Weekly Tracker'!$G$2:$G$766),"") | H8: =IFERROR(LOOKUP(2,1/('Weekly Tracker'!$E$2:$E$766=$A8)/('Weekly Tracker'!$H$2:$H$766<>""),'Weekly Tracker'!$H$2:$H$766),"") | I8: =IF(H8<>"",LOOKUP(2,1/('Weekly Tracker'!$E$2:$E$766=$A8)/('Weekly Tracker'!$H$2:$H$766<>""),'Weekly Tracker'!$I$2:$I$766),"") | J8: =IFERROR(LOOKUP(2,1/('Weekly Tracker'!$E$2:$E$766=$A8)/('Weekly Tracker'!$J$2:$J$766<>""),'Weekly Tracker'!$J$2:$J$766),"") | K8: =IFERROR(LOOKUP(2,1/('Weekly Tracker'!$E$2:$E$766=$A8)/('Weekly Tracker'!$N$2:$N$766<>""),'Weekly Tracker'!$N$2:$N$766),"") | L8: =IFERROR(LOOKUP(2,1/('Weekly Tracker'!$E$2:$E$766=$A8)/('Weekly Tracker'!$O$2:$O$766<>""),'Weekly Tracker'!$O$2:$O$766),"")
A9: Vinoth Mech | B9: 8015927970 | F9: =IFERROR(LOOKUP(2,1/('Weekly Tracker'!$E$2:$E$766=$A9)/('Weekly Tracker'!$F$2:$F$766<>""),'Weekly Tracker'!$F$2:$F$766),"") | G9: =IF(F9<>"",LOOKUP(2,1/('Weekly Tracker'!$E$2:$E$766=$A9)/('Weekly Tracker'!$F$2:$F$766<>""),'Weekly Tracker'!$G$2:$G$766),"") | H9: =IFERROR(LOOKUP(2,1/('Weekly Tracker'!$E$2:$E$766=$A9)/('Weekly Tracker'!$H$2:$H$766<>""),'Weekly Tracker'!$H$2:$H$766),"") | I9: =IF(H9<>"",LOOKUP(2,1/('Weekly Tracker'!$E$2:$E$766=$A9)/('Weekly Tracker'!$H$2:$H$766<>""),'Weekly Tracker'!$I$2:$I$766),"") | J9: =IFERROR(LOOKUP(2,1/('Weekly Tracker'!$E$2:$E$766=$A9)/('Weekly Tracker'!$J$2:$J$766<>""),'Weekly Tracker'!$J$2:$J$766),"") | K9: =IFERROR(LOOKUP(2,1/('Weekly Tracker'!$E$2:$E$766=$A9)/('Weekly Tracker'!$N$2:$N$766<>""),'Weekly Tracker'!$N$2:$N$766),"") | L9: =IFERROR(LOOKUP(2,1/('Weekly Tracker'!$E$2:$E$766=$A9)/('Weekly Tracker'!$O$2:$O$766<>""),'Weekly Tracker'!$O$2:$O$766),"")
A10: Mani Kandan FB | B10: 971554780531, +971 55 478 0531 | F10: =IFERROR(LOOKUP(2,1/('Weekly Tracker'!$E$2:$E$766=$A10)/('Weekly Tracker'!$F$2:$F$766<>""),'Weekly Tracker'!$F$2:$F$766),"") | G10: =IF(F10<>"",LOOKUP(2,1/('Weekly Tracker'!$E$2:$E$766=$A10)/('Weekly Tracker'!$F$2:$F$766<>""),'Weekly Tracker'!$G$2:$G$766),"") | H10: =IFERROR(LOOKUP(2,1/('Weekly Tracker'!$E$2:$E$766=$A10)/('Weekly Tracker'!$H$2:$H$766<>""),'Weekly Tracker'!$H$2:$H$766),"") | I10: =IF(H10<>"",LOOKUP(2,1/('Weekly Tracker'!$E$2:$E$766=$A10)/('Weekly Tracker'!$H$2:$H$766<>""),'Weekly Tracker'!$I$2:$I$766),"") | J10: =IFERROR(LOOKUP(2,1/('Weekly Tracker'!$E$2:$E$766=$A10)/('Weekly Tracker'!$J$2:$J$766<>""),'Weekly Tracker'!$J$2:$J$766),"") | K10: =IFERROR(LOOKUP(2,1/('Weekly Tracker'!$E$2:$E$766=$A10)/('Weekly Tracker'!$N$2:$N$766<>""),'Weekly Tracker'!$N$2:$N$766),"") | L10: =IFERROR(LOOKUP(2,1/('Weekly Tracker'!$E$2:$E$766=$A10)/('Weekly Tracker'!$O$2:$O$766<>""),'Weekly Tracker'!$O$2:$O$766),"")
A11: Mani VJ FB | B11: 917904326199 | F11: =IFERROR(LOOKUP(2,1/('Weekly Tracker'!$E$2:$E$766=$A11)/('Weekly Tracker'!$F$2:$F$766<>""),'Weekly Tracker'!$F$2:$F$766),"") | G11: =IF(F11<>"",LOOKUP(2,1/('Weekly Tracker'!$E$2:$E$766=$A11)/('Weekly Tracker'!$F$2:$F$766<>""),'Weekly Tracker'!$G$2:$G$766),"") | H11: =IFERROR(LOOKUP(2,1/('Weekly Tracker'!$E$2:$E$766=$A11)/('Weekly Tracker'!$H$2:$H$766<>""),'Weekly Tracker'!$H$2:$H$766),"") | I11: =IF(H11<>"",LOOKUP(2,1/('Weekly Tracker'!$E$2:$E$766=$A11)/('Weekly Tracker'!$H$2:$H$766<>""),'Weekly Tracker'!$I$2:$I$766),"") | J11: =IFERROR(LOOKUP(2,1/('Weekly Tracker'!$E$2:$E$766=$A11)/('Weekly Tracker'!$J$2:$J$766<>""),'Weekly Tracker'!$J$2:$J$766),"") | K11: =IFERROR(LOOKUP(2,1/('Weekly Tracker'!$E$2:$E$766=$A11)/('Weekly Tracker'!$N$2:$N$766<>""),'Weekly Tracker'!$N$2:$N$766),"") | L11: =IFERROR(LOOKUP(2,1/('Weekly Tracker'!$E$2:$E$766=$A11)/('Weekly Tracker'!$O$2:$O$766<>""),'Weekly Tracker'!$O$2:$O$766),"")
A12: Niranjan Urja | F12: =IFERROR(LOOKUP(2,1/('Weekly Tracker'!$E$2:$E$766=$A12)/('Weekly Tracker'!$F$2:$F$766<>""),'Weekly Tracker'!$F$2:$F$766),"") | G12: =IF(F12<>"",LOOKUP(2,1/('Weekly Tracker'!$E$2:$E$766=$A12)/('Weekly Tracker'!$F$2:$F$766<>""),'Weekly Tracker'!$G$2:$G$766),"") | H12: =IFERROR(LOOKUP(2,1/('Weekly Tracker'!$E$2:$E$766=$A12)/('Weekly Tracker'!$H$2:$H$766<>""),'Weekly Tracker'!$H$2:$H$766),"") | I12: =IF(H12<>"",LOOKUP(2,1/('Weekly Tracker'!$E$2:$E$766=$A12)/('Weekly Tracker'!$H$2:$H$766<>""),'Weekly Tracker'!$I$2:$I$766),"") | J12: =IFERROR(LOOKUP(2,1/('Weekly Tracker'!$E$2:$E$766=$A12)/('Weekly Tracker'!$J$2:$J$766<>""),'Weekly Tracker'!$J$2:$J$766),"") | K12: =IFERROR(LOOKUP(2,1/('Weekly Tracker'!$E$2:$E$766=$A12)/('Weekly Tracker'!$N$2:$N$766<>""),'Weekly Tracker'!$N$2:$N$766),"") | L12: =IFERROR(LOOKUP(2,1/('Weekly Tracker'!$E$2:$E$766=$A12)/('Weekly Tracker'!$O$2:$O$766<>""),'Weekly Tracker'!$O$2:$O$766),"")
A13: Anbu Urja | B13: 917418262653 | F13: =IFERROR(LOOKUP(2,1/('Weekly Tracker'!$E$2:$E$766=$A13)/('Weekly Tracker'!$F$2:$F$766<>""),'Weekly Tracker'!$F$2:$F$766),"") | G13: =IF(F13<>"",LOOKUP(2,1/('Weekly Tracker'!$E$2:$E$766=$A13)/('Weekly Tracker'!$F$2:$F$766<>""),'Weekly Tracker'!$G$2:$G$766),"") | H13: =IFERROR(LOOKUP(2,1/('Weekly Tracker'!$E$2:$E$766=$A13)/('Weekly Tracker'!$H$2:$H$766<>""),'Weekly Tracker'!$H$2:$H$766),"") | I13: =IF(H13<>"",LOOKUP(2,1/('Weekly Tracker'!$E$2:$E$766=$A13)/('Weekly Tracker'!$H$2:$H$766<>""),'Weekly Tracker'!$I$2:$I$766),"") | J13: =IFERROR(LOOKUP(2,1/('Weekly Tracker'!$E$2:$E$766=$A13)/('Weekly Tracker'!$J$2:$J$766<>""),'Weekly Tracker'!$J$2:$J$766),"") | K13: =IFERROR(LOOKUP(2,1/('Weekly Tracker'!$E$2:$E$766=$A13)/('Weekly Tracker'!$N$2:$N$766<>""),'Weekly Tracker'!$N$2:$N$766),"") | L13: =IFERROR(LOOKUP(2,1/('Weekly Tracker'!$E$2:$E$766=$A13)/('Weekly Tracker'!$O$2:$O$766<>""),'Weekly Tracker'!$O$2:$O$766),"")
A14: Vinoth Kumar Mech | B14: 919099102966, +91 90991 02966, 919655485302 | F14: =IFERROR(LOOKUP(2,1/('Weekly Tracker'!$E$2:$E$766=$A14)/('Weekly Tracker'!$F$2:$F$766<>""),'Weekly Tracker'!$F$2:$F$766),"") | G14: =IF(F14<>"",LOOKUP(2,1/('Weekly Tracker'!$E$2:$E$766=$A14)/('Weekly Tracker'!$F$2:$F$766<>""),'Weekly Tracker'!$G$2:$G$766),"") | H14: =IFERROR(LOOKUP(2,1/('Weekly Tracker'!$E$2:$E$766=$A14)/('Weekly Tracker'!$H$2:$H$766<>""),'Weekly Tracker'!$H$2:$H$766),"") | I14: =IF(H14<>"",LOOKUP(2,1/('Weekly Tracker'!$E$2:$E$766=$A14)/('Weekly Tracker'!$H$2:$H$766<>""),'Weekly Tracker'!$I$2:$I$766),"") | J14: =IFERROR(LOOKUP(2,1/('Weekly Tracker'!$E$2:$E$766=$A14)/('Weekly Tracker'!$J$2:$J$766<>""),'Weekly Tracker'!$J$2:$J$766),"") | K14: =IFERROR(LOOKUP(2,1/('Weekly Tracker'!$E$2:$E$766=$A14)/('Weekly Tracker'!$N$2:$N$766<>""),'Weekly Tracker'!$N$2:$N$766),"") | L14: =IFERROR(LOOKUP(2,1/('Weekly Tracker'!$E$2:$E$766=$A14)/('Weekly Tracker'!$O$2:$O$766<>""),'Weekly Tracker'!$O$2:$O$766),"")
A15: Manikandan FB | B15: 7639748654, 9965410728, 99654 10728 | F15: =IFERROR(LOOKUP(2,1/('Weekly Tracker'!$E$2:$E$766=$A15)/('Weekly Tracker'!$F$2:$F$766<>""),'Weekly Tracker'!$F$2:$F$766),"") | G15: =IF(F15<>"",LOOKUP(2,1/('Weekly Tracker'!$E$2:$E$766=$A15)/('Weekly Tracker'!$F$2:$F$766<>""),'Weekly Tracker'!$G$2:$G$766),"") | H15: =IFERROR(LOOKUP(2,1/('Weekly Tracker'!$E$2:$E$766=$A15)/('Weekly Tracker'!$H$2:$H$766<>""),'Weekly Tracker'!$H$2:$H$766),"") | I15: =IF(H15<>"",LOOKUP(2,1/('Weekly Tracker'!$E$2:$E$766=$A15)/('Weekly Tracker'!$H$2:$H$766<>""),'Weekly Tracker'!$I$2:$I$766),"") | J15: =IFERROR(LOOKUP(2,1/('Weekly Tracker'!$E$2:$E$766=$A15)/('Weekly Tracker'!$J$2:$J$766<>""),'Weekly Tracker'!$J$2:$J$766),"") | K15: =IFERROR(LOOKUP(2,1/('Weekly Tracker'!$E$2:$E$766=$A15)/('Weekly Tracker'!$N$2:$N$766<>""),'Weekly Tracker'!$N$2:$N$766),"") | L15: =IFERROR(LOOKUP(2,1/('Weekly Tracker'!$E$2:$E$766=$A15)/('Weekly Tracker'!$O$2:$O$766<>""),'Weekly Tracker'!$O$2:$O$766),"")
A16: Urjanet | F16: =IFERROR(LOOKUP(2,1/('Weekly Tracker'!$E$2:$E$766=$A16)/('Weekly Tracker'!$F$2:$F$766<>""),'Weekly Tracker'!$F$2:$F$766),"") | G16: =IF(F16<>"",LOOKUP(2,1/('Weekly Tracker'!$E$2:$E$766=$A16)/('Weekly Tracker'!$F$2:$F$766<>""),'Weekly Tracker'!$G$2:$G$766),"") | H16: =IFERROR(LOOKUP(2,1/('Weekly Tracker'!$E$2:$E$766=$A16)/('Weekly Tracker'!$H$2:$H$766<>""),'Weekly Tracker'!$H$2:$H$766),"") | I16: =IF(H16<>"",LOOKUP(2,1/('Weekly Tracker'!$E$2:$E$766=$A16)/('Weekly Tracker'!$H$2:$H$766<>""),'Weekly Tracker'!$I$2:$I$766),"") | J16: =IFERROR(LOOKUP(2,1/('Weekly Tracker'!$E$2:$E$766=$A16)/('Weekly Tracker'!$J$2:$J$766<>""),'Weekly Tracker'!$J$2:$J$766),"") | K16: =IFERROR(LOOKUP(2,1/('Weekly Tracker'!$E$2:$E$766=$A16)/('Weekly Tracker'!$N$2:$N$766<>""),'Weekly Tracker'!$N$2:$N$766),"") | L16: =IFERROR(LOOKUP(2,1/('Weekly Tracker'!$E$2:$E$766=$A16)/('Weekly Tracker'!$O$2:$O$766<>""),'Weekly Tracker'!$O$2:$O$766),"")
A17: Verizon | F17: =IFERROR(LOOKUP(2,1/('Weekly Tracker'!$E$2:$E$766=$A17)/('Weekly Tracker'!$F$2:$F$766<>""),'Weekly Tracker'!$F$2:$F$766),"") | G17: =IF(F17<>"",LOOKUP(2,1/('Weekly Tracker'!$E$2:$E$766=$A17)/('Weekly Tracker'!$F$2:$F$766<>""),'Weekly Tracker'!$G$2:$G$766),"") | H17: =IFERROR(LOOKUP(2,1/('Weekly Tracker'!$E$2:$E$766=$A17)/('Weekly Tracker'!$H$2:$H$766<>""),'Weekly Tracker'!$H$2:$H$766),"") | I17: =IF(H17<>"",LOOKUP(2,1/('Weekly Tracker'!$E$2:$E$766=$A17)/('Weekly Tracker'!$H$2:$H$766<>""),'Weekly Tracker'!$I$2:$I$766),"") | J17: =IFERROR(LOOKUP(2,1/('Weekly Tracker'!$E$2:$E$766=$A17)/('Weekly Tracker'!$J$2:$J$766<>""),'Weekly Tracker'!$J$2:$J$766),"") | K17: =IFERROR(LOOKUP(2,1/('Weekly Tracker'!$E$2:$E$766=$A17)/('Weekly Tracker'!$N$2:$N$766<>""),'Weekly Tracker'!$N$2:$N$766),"") | L17: =IFERROR(LOOKUP(2,1/('Weekly Tracker'!$E$2:$E$766=$A17)/('Weekly Tracker'!$O$2:$O$766<>""),'Weekly Tracker'!$O$2:$O$766),"")
A18: School | F18: =IFERROR(LOOKUP(2,1/('Weekly Tracker'!$E$2:$E$766=$A18)/('Weekly Tracker'!$F$2:$F$766<>""),'Weekly Tracker'!$F$2:$F$766),"") | G18: =IF(F18<>"",LOOKUP(2,1/('Weekly Tracker'!$E$2:$E$766=$A18)/('Weekly Tracker'!$F$2:$F$766<>""),'Weekly Tracker'!$G$2:$G$766),"") | H18: =IFERROR(LOOKUP(2,1/('Weekly Tracker'!$E$2:$E$766=$A18)/('Weekly Tracker'!$H$2:$H$766<>""),'Weekly Tracker'!$H$2:$H$766),"") | I18: =IF(H18<>"",LOOKUP(2,1/('Weekly Tracker'!$E$2:$E$766=$A18)/('Weekly Tracker'!$H$2:$H$766<>""),'Weekly Tracker'!$I$2:$I$766),"") | J18: =IFERROR(LOOKUP(2,1/('Weekly Tracker'!$E$2:$E$766=$A18)/('Weekly Tracker'!$J$2:$J$766<>""),'Weekly Tracker'!$J$2:$J$766),"") | K18: =IFERROR(LOOKUP(2,1/('Weekly Tracker'!$E$2:$E$766=$A18)/('Weekly Tracker'!$N$2:$N$766<>""),'Weekly Tracker'!$N$2:$N$766),"") | L18: =IFERROR(LOOKUP(2,1/('Weekly Tracker'!$E$2:$E$766=$A18)/('Weekly Tracker'!$O$2:$O$766<>""),'Weekly Tracker'!$O$2:$O$766),"")
A19: Mathan Kumar FB | B19: 6380108044, 9092455151, 90924 55151 | F19: =IFERROR(LOOKUP(2,1/('Weekly Tracker'!$E$2:$E$766=$A19)/('Weekly Tracker'!$F$2:$F$766<>""),'Weekly Tracker'!$F$2:$F$766),"") | G19: =IF(F19<>"",LOOKUP(2,1/('Weekly Tracker'!$E$2:$E$766=$A19)/('Weekly Tracker'!$F$2:$F$766<>""),'Weekly Tracker'!$G$2:$G$766),"") | H19: =IFERROR(LOOKUP(2,1/('Weekly Tracker'!$E$2:$E$766=$A19)/('Weekly Tracker'!$H$2:$H$766<>""),'Weekly Tracker'!$H$2:$H$766),"") | I19: =IF(H19<>"",LOOKUP(2,1/('Weekly Tracker'!$E$2:$E$766=$A19)/('Weekly Tracker'!$H$2:$H$766<>""),'Weekly Tracker'!$I$2:$I$766),"") | J19: =IFERROR(LOOKUP(2,1/('Weekly Tracker'!$E$2:$E$766=$A19)/('Weekly Tracker'!$J$2:$J$766<>""),'Weekly Tracker'!$J$2:$J$766),"") | K19: =IFERROR(LOOKUP(2,1/('Weekly Tracker'!$E$2:$E$766=$A19)/('Weekly Tracker'!$N$2:$N$766<>""),'Weekly Tracker'!$N$2:$N$766),"") | L19: =IFERROR(LOOKUP(2,1/('Weekly Tracker'!$E$2:$E$766=$A19)/('Weekly Tracker'!$O$2:$O$766<>""),'Weekly Tracker'!$O$2:$O$766),"")
A20: Mani Jaikrish FB | B20: 919206477402, +91 92064 77402 | F20: =IFERROR(LOOKUP(2,1/('Weekly Tracker'!$E$2:$E$766=$A20)/('Weekly Tracker'!$F$2:$F$766<>""),'Weekly Tracker'!$F$2:$F$766),"") | G20: =IF(F20<>"",LOOKUP(2,1/('Weekly Tracker'!$E$2:$E$766=$A20)/('Weekly Tracker'!$F$2:$F$766<>""),'Weekly Tracker'!$G$2:$G$766),"") | H20: =IFERROR(LOOKUP(2,1/('Weekly Tracker'!$E$2:$E$766=$A20)/('Weekly Tracker'!$H$2:$H$766<>""),'Weekly Tracker'!$H$2:$H$766),"") | I20: =IF(H20<>"",LOOKUP(2,1/('Weekly Tracker'!$E$2:$E$766=$A20)/('Weekly Tracker'!$H$2:$H$766<>""),'Weekly Tracker'!$I$2:$I$766),"") | J20: =IFERROR(LOOKUP(2,1/('Weekly Tracker'!$E$2:$E$766=$A20)/('Weekly Tracker'!$J$2:$J$766<>""),'Weekly Tracker'!$J$2:$J$766),"") | K20: =IFERROR(LOOKUP(2,1/('Weekly Tracker'!$E$2:$E$766=$A20)/('Weekly Tracker'!$N$2:$N$766<>""),'Weekly Tracker'!$N$2:$N$766),"") | L20: =IFERROR(LOOKUP(2,1/('Weekly Tracker'!$E$2:$E$766=$A20)/('Weekly Tracker'!$O$2:$O$766<>""),'Weekly Tracker'!$O$2:$O$766),"")
A21: Ajith Kumar Grp Ucen | B21: 917402769024 | F21: =IFERROR(LOOKUP(2,1/('Weekly Tracker'!$E$2:$E$766=$A21)/('Weekly Tracker'!$F$2:$F$766<>""),'Weekly Tracker'!$F$2:$F$766),"") | G21: =IF(F21<>"",LOOKUP(2,1/('Weekly Tracker'!$E$2:$E$766=$A21)/('Weekly Tracker'!$F$2:$F$766<>""),'Weekly Tracker'!$G$2:$G$766),"") | H21: =IFERROR(LOOKUP(2,1/('Weekly Tracker'!$E$2:$E$766=$A21)/('Weekly Tracker'!$H$2:$H$766<>""),'Weekly Tracker'!$H$2:$H$766),"") | I21: =IF(H21<>"",LOOKUP(2,1/('Weekly Tracker'!$E$2:$E$766=$A21)/('Weekly Tracker'!$H$2:$H$766<>""),'Weekly Tracker'!$I$2:$I$766),"") | J21: =IFERROR(LOOKUP(2,1/('Weekly Tracker'!$E$2:$E$766=$A21)/('Weekly Tracker'!$J$2:$J$766<>""),'Weekly Tracker'!$J$2:$J$766),"") | K21: =IFERROR(LOOKUP(2,1/('Weekly Tracker'!$E$2:$E$766=$A21)/('Weekly Tracker'!$N$2:$N$766<>""),'Weekly Tracker'!$N$2:$N$766),"") | L21: =IFERROR(LOOKUP(2,1/('Weekly Tracker'!$E$2:$E$766=$A21)/('Weekly Tracker'!$O$2:$O$766<>""),'Weekly Tracker'!$O$2:$O$766),"")
A22: VP VenkadeshaPerumal | B22: 8807791011 | F22: =IFERROR(LOOKUP(2,1/('Weekly Tracker'!$E$2:$E$766=$A22)/('Weekly Tracker'!$F$2:$F$766<>""),'Weekly Tracker'!$F$2:$F$766),"") | G22: =IF(F22<>"",LOOKUP(2,1/('Weekly Tracker'!$E$2:$E$766=$A22)/('Weekly Tracker'!$F$2:$F$766<>""),'Weekly Tracker'!$G$2:$G$766),"") | H22: =IFERROR(LOOKUP(2,1/('Weekly Tracker'!$E$2:$E$766=$A22)/('Weekly Tracker'!$H$2:$H$766<>""),'Weekly Tracker'!$H$2:$H$766),"") | I22: =IF(H22<>"",LOOKUP(2,1/('Weekly Tracker'!$E$2:$E$766=$A22)/('Weekly Tracker'!$H$2:$H$766<>""),'Weekly Tracker'!$I$2:$I$766),"") | J22: =IFERROR(LOOKUP(2,1/('Weekly Tracker'!$E$2:$E$766=$A22)/('Weekly Tracker'!$J$2:$J$766<>""),'Weekly Tracker'!$J$2:$J$766),"") | K22: =IFERROR(LOOKUP(2,1/('Weekly Tracker'!$E$2:$E$766=$A22)/('Weekly Tracker'!$N$2:$N$766<>""),'Weekly Tracker'!$N$2:$N$766),"") | L22: =IFERROR(LOOKUP(2,1/('Weekly Tracker'!$E$2:$E$766=$A22)/('Weekly Tracker'!$O$2:$O$766<>""),'Weekly Tracker'!$O$2:$O$766),"")
A23: Rakesh TL Urja | B23: 919791063268 | F23: =IFERROR(LOOKUP(2,1/('Weekly Tracker'!$E$2:$E$766=$A23)/('Weekly Tracker'!$F$2:$F$766<>""),'Weekly Tracker'!$F$2:$F$766),"") | G23: =IF(F23<>"",LOOKUP(2,1/('Weekly Tracker'!$E$2:$E$766=$A23)/('Weekly Tracker'!$F$2:$F$766<>""),'Weekly Tracker'!$G$2:$G$766),"") | H23: =IFERROR(LOOKUP(2,1/('Weekly Tracker'!$E$2:$E$766=$A23)/('Weekly Tracker'!$H$2:$H$766<>""),'Weekly Tracker'!$H$2:$H$766),"") | I23: =IF(H23<>"",LOOKUP(2,1/('Weekly Tracker'!$E$2:$E$766=$A23)/('Weekly Tracker'!$H$2:$H$766<>""),'Weekly Tracker'!$I$2:$I$766),"") | J23: =IFERROR(LOOKUP(2,1/('Weekly Tracker'!$E$2:$E$766=$A23)/('Weekly Tracker'!$J$2:$J$766<>""),'Weekly Tracker'!$J$2:$J$766),"") | K23: =IFERROR(LOOKUP(2,1/('Weekly Tracker'!$E$2:$E$766=$A23)/('Weekly Tracker'!$N$2:$N$766<>""),'Weekly Tracker'!$N$2:$N$766),"") | L23: =IFERROR(LOOKUP(2,1/('Weekly Tracker'!$E$2:$E$766=$A23)/('Weekly Tracker'!$O$2:$O$766<>""),'Weekly Tracker'!$O$2:$O$766),"")
A24: Anbu Arasan Urja | B24: 917418262653, 919626452984 | F24: =IFERROR(LOOKUP(2,1/('Weekly Tracker'!$E$2:$E$766=$A24)/('Weekly Tracker'!$F$2:$F$766<>""),'Weekly Tracker'!$F$2:$F$766),"") | G24: =IF(F24<>"",LOOKUP(2,1/('Weekly Tracker'!$E$2:$E$766=$A24)/('Weekly Tracker'!$F$2:$F$766<>""),'Weekly Tracker'!$G$2:$G$766),"") | H24: =IFERROR(LOOKUP(2,1/('Weekly Tracker'!$E$2:$E$766=$A24)/('Weekly Tracker'!$H$2:$H$766<>""),'Weekly Tracker'!$H$2:$H$766),"") | I24: =IF(H24<>"",LOOKUP(2,1/('Weekly Tracker'!$E$2:$E$766=$A24)/('Weekly Tracker'!$H$2:$H$766<>""),'Weekly Tracker'!$I$2:$I$766),"") | J24: =IFERROR(LOOKUP(2,1/('Weekly Tracker'!$E$2:$E$766=$A24)/('Weekly Tracker'!$J$2:$J$766<>""),'Weekly Tracker'!$J$2:$J$766),"") | K24: =IFERROR(LOOKUP(2,1/('Weekly Tracker'!$E$2:$E$766=$A24)/('Weekly Tracker'!$N$2:$N$766<>""),'Weekly Tracker'!$N$2:$N$766),"") | L24: =IFERROR(LOOKUP(2,1/('Weekly Tracker'!$E$2:$E$766=$A24)/('Weekly Tracker'!$O$2:$O$766<>""),'Weekly Tracker'!$O$2:$O$766),"")
A25: Suresh Dada FB | B25: 919489801803 | F25: =IFERROR(LOOKUP(2,1/('Weekly Tracker'!$E$2:$E$766=$A25)/('Weekly Tracker'!$F$2:$F$766<>""),'Weekly Tracker'!$F$2:$F$766),"") | G25: =IF(F25<>"",LOOKUP(2,1/('Weekly Tracker'!$E$2:$E$766=$A25)/('Weekly Tracker'!$F$2:$F$766<>""),'Weekly Tracker'!$G$2:$G$766),"") | H25: =IFERROR(LOOKUP(2,1/('Weekly Tracker'!$E$2:$E$766=$A25)/('Weekly Tracker'!$H$2:$H$766<>""),'Weekly Tracker'!$H$2:$H$766),"") | I25: =IF(H25<>"",LOOKUP(2,1/('Weekly Tracker'!$E$2:$E$766=$A25)/('Weekly Tracker'!$H$2:$H$766<>""),'Weekly Tracker'!$I$2:$I$766),"") | J25: =IFERROR(LOOKUP(2,1/('Weekly Tracker'!$E$2:$E$766=$A25)/('Weekly Tracker'!$J$2:$J$766<>""),'Weekly Tracker'!$J$2:$J$766),"") | K25: =IFERROR(LOOKUP(2,1/('Weekly Tracker'!$E$2:$E$766=$A25)/('Weekly Tracker'!$N$2:$N$766<>""),'Weekly Tracker'!$N$2:$N$766),"") | L25: =IFERROR(LOOKUP(2,1/('Weekly Tracker'!$E$2:$E$766=$A25)/('Weekly Tracker'!$O$2:$O$766<>""),'Weekly Tracker'!$O$2:$O$766),"")
A26: Bala Murugan FB | B26: 9486622065, 7598704205, +91 91762 46373, 94866 22065 | F26: =IFERROR(LOOKUP(2,1/('Weekly Tracker'!$E$2:$E$766=$A26)/('Weekly Tracker'!$F$2:$F$766<>""),'Weekly Tracker'!$F$2:$F$766),"") | G26: =IF(F26<>"",LOOKUP(2,1/('Weekly Tracker'!$E$2:$E$766=$A26)/('Weekly Tracker'!$F$2:$F$766<>""),'Weekly Tracker'!$G$2:$G$766),"") | H26: =IFERROR(LOOKUP(2,1/('Weekly Tracker'!$E$2:$E$766=$A26)/('Weekly Tracker'!$H$2:$H$766<>""),'Weekly Tracker'!$H$2:$H$766),"") | I26: =IF(H26<>"",LOOKUP(2,1/('Weekly Tracker'!$E$2:$E$766=$A26)/('Weekly Tracker'!$H$2:$H$766<>""),'Weekly Tracker'!$I$2:$I$766),"") | J26: =IFERROR(LOOKUP(2,1/('Weekly Tracker'!$E$2:$E$766=$A26)/('Weekly Tracker'!$J$2:$J$766<>""),'Weekly Tracker'!$J$2:$J$766),"") | K26: =IFERROR(LOOKUP(2,1/('Weekly Tracker'!$E$2:$E$766=$A26)/('Weekly Tracker'!$N$2:$N$766<>""),'Weekly Tracker'!$N$2:$N$766),"") | L26: =IFERROR(LOOKUP(2,1/('Weekly Tracker'!$E$2:$E$766=$A26)/('Weekly Tracker'!$O$2:$O$766<>""),'Weekly Tracker'!$O$2:$O$766),"")
A27: Rajesh Sekar FB | B27: 917639239885, +91 76392 39885 | F27: =IFERROR(LOOKUP(2,1/('Weekly Tracker'!$E$2:$E$766=$A27)/('Weekly Tracker'!$F$2:$F$766<>""),'Weekly Tracker'!$F$2:$F$766),"") | G27: =IF(F27<>"",LOOKUP(2,1/('Weekly Tracker'!$E$2:$E$766=$A27)/('Weekly Tracker'!$F$2:$F$766<>""),'Weekly Tracker'!$G$2:$G$766),"") | H27: =IFERROR(LOOKUP(2,1/('Weekly Tracker'!$E$2:$E$766=$A27)/('Weekly Tracker'!$H$2:$H$766<>""),'Weekly Tracker'!$H$2:$H$766),"") | I27: =IF(H27<>"",LOOKUP(2,1/('Weekly Tracker'!$E$2:$E$766=$A27)/('Weekly Tracker'!$H$2:$H$766<>""),'Weekly Tracker'!$I$2:$I$766),"") | J27: =IFERROR(LOOKUP(2,1/('Weekly Tracker'!$E$2:$E$766=$A27)/('Weekly Tracker'!$J$2:$J$766<>""),'Weekly Tracker'!$J$2:$J$766),"") | K27: =IFERROR(LOOKUP(2,1/('Weekly Tracker'!$E$2:$E$766=$A27)/('Weekly Tracker'!$N$2:$N$766<>""),'Weekly Tracker'!$N$2:$N$766),"") | L27: =IFERROR(LOOKUP(2,1/('Weekly Tracker'!$E$2:$E$766=$A27)/('Weekly Tracker'!$O$2:$O$766<>""),'Weekly Tracker'!$O$2:$O$766),"")
A28: Sai Adithya FB | B28: 917358758870 | F28: =IFERROR(LOOKUP(2,1/('Weekly Tracker'!$E$2:$E$766=$A28)/('Weekly Tracker'!$F$2:$F$766<>""),'Weekly Tracker'!$F$2:$F$766),"") | G28: =IF(F28<>"",LOOKUP(2,1/('Weekly Tracker'!$E$2:$E$766=$A28)/('Weekly Tracker'!$F$2:$F$766<>""),'Weekly Tracker'!$G$2:$G$766),"") | H28: =IFERROR(LOOKUP(2,1/('Weekly Tracker'!$E$2:$E$766=$A28)/('Weekly Tracker'!$H$2:$H$766<>""),'Weekly Tracker'!$H$2:$H$766),"") | I28: =IF(H28<>"",LOOKUP(2,1/('Weekly Tracker'!$E$2:$E$766=$A28)/('Weekly Tracker'!$H$2:$H$766<>""),'Weekly Tracker'!$I$2:$I$766),"") | J28: =IFERROR(LOOKUP(2,1/('Weekly Tracker'!$E$2:$E$766=$A28)/('Weekly Tracker'!$J$2:$J$766<>""),'Weekly Tracker'!$J$2:$J$766),"") | K28: =IFERROR(LOOKUP(2,1/('Weekly Tracker'!$E$2:$E$766=$A28)/('Weekly Tracker'!$N$2:$N$766<>""),'Weekly Tracker'!$N$2:$N$766),"") | L28: =IFERROR(LOOKUP(2,1/('Weekly Tracker'!$E$2:$E$766=$A28)/('Weekly Tracker'!$O$2:$O$766<>""),'Weekly Tracker'!$O$2:$O$766),"")
A29: Niranjan Past Urja | B29: 918939230269 | F29: =IFERROR(LOOKUP(2,1/('Weekly Tracker'!$E$2:$E$766=$A29)/('Weekly Tracker'!$F$2:$F$766<>""),'Weekly Tracker'!$F$2:$F$766),"") | G29: =IF(F29<>"",LOOKUP(2,1/('Weekly Tracker'!$E$2:$E$766=$A29)/('Weekly Tracker'!$F$2:$F$766<>""),'Weekly Tracker'!$G$2:$G$766),"") | H29: =IFERROR(LOOKUP(2,1/('Weekly Tracker'!$E$2:$E$766=$A29)/('Weekly Tracker'!$H$2:$H$766<>""),'Weekly Tracker'!$H$2:$H$766),"") | I29: =IF(H29<>"",LOOKUP(2,1/('Weekly Tracker'!$E$2:$E$766=$A29)/('Weekly Tracker'!$H$2:$H$766<>""),'Weekly Tracker'!$I$2:$I$766),"") | J29: =IFERROR(LOOKUP(2,1/('Weekly Tracker'!$E$2:$E$766=$A29)/('Weekly Tracker'!$J$2:$J$766<>""),'Weekly Tracker'!$J$2:$J$766),"") | K29: =IFERROR(LOOKUP(2,1/('Weekly Tracker'!$E$2:$E$766=$A29)/('Weekly Tracker'!$N$2:$N$766<>""),'Weekly Tracker'!$N$2:$N$766),"") | L29: =IFERROR(LOOKUP(2,1/('Weekly Tracker'!$E$2:$E$766=$A29)/('Weekly Tracker'!$O$2:$O$766<>""),'Weekly Tracker'!$O$2:$O$766),"")
A30: Ajith Kumar Grp UCEN | B30: 919655944652 | F30: =IFERROR(LOOKUP(2,1/('Weekly Tracker'!$E$2:$E$766=$A30)/('Weekly Tracker'!$F$2:$F$766<>""),'Weekly Tracker'!$F$2:$F$766),"") | G30: =IF(F30<>"",LOOKUP(2,1/('Weekly Tracker'!$E$2:$E$766=$A30)/('Weekly Tracker'!$F$2:$F$766<>""),'Weekly Tracker'!$G$2:$G$766),"") | H30: =IFERROR(LOOKUP(2,1/('Weekly Tracker'!$E$2:$E$766=$A30)/('Weekly Tracker'!$H$2:$H$766<>""),'Weekly Tracker'!$H$2:$H$766),"") | I30: =IF(H30<>"",LOOKUP(2,1/('Weekly Tracker'!$E$2:$E$766=$A30)/('Weekly Tracker'!$H$2:$H$766<>""),'Weekly Tracker'!$I$2:$I$766),"") | J30: =IFERROR(LOOKUP(2,1/('Weekly Tracker'!$E$2:$E$766=$A30)/('Weekly Tracker'!$J$2:$J$766<>""),'Weekly Tracker'!$J$2:$J$766),"") | K30: =IFERROR(LOOKUP(2,1/('Weekly Tracker'!$E$2:$E$766=$A30)/('Weekly Tracker'!$N$2:$N$766<>""),'Weekly Tracker'!$N$2:$N$766),"") | L30: =IFERROR(LOOKUP(2,1/('Weekly Tracker'!$E$2:$E$766=$A30)/('Weekly Tracker'!$O$2:$O$766<>""),'Weekly Tracker'!$O$2:$O$766),"")
... A138: Ajin (Nishanth) | B138: 919791370484 | F138: =IFERROR(LOOKUP(2,1/('Weekly Tracker'!$E$2:$E$766=$A138)/('Weekly Tracker'!$F$2:$F$766<>""),'Weekly Tracker'!$F$2:$F$766),"") | G138: =IF(F138<>"",LOOKUP(2,1/('Weekly Tracker'!$E$2:$E$766=$A138)/('Weekly Tracker'!$F$2:$F$766<>""),'Weekly Tracker'!$G$2:$G$766),"") | H138: =IFERROR(LOOKUP(2,1/('Weekly Tracker'!$E$2:$E$766=$A138)/('Weekly Tracker'!$H$2:$H$766<>""),'Weekly Tracker'!$H$2:$H$766),"") | I138: =IF(H138<>"",LOOKUP(2,1/('Weekly Tracker'!$E$2:$E$766=$A138)/('Weekly Tracker'!$H$2:$H$766<>""),'Weekly Tracker'!$I$2:$I$766),"") | J138: =IFERROR(LOOKUP(2,1/('Weekly Tracker'!$E$2:$E$766=$A138)/('Weekly Tracker'!$J$2:$J$766<>""),'Weekly Tracker'!$J$2:$J$766),"") | K138: =IFERROR(LOOKUP(2,1/('Weekly Tracker'!$E$2:$E$766=$A138)/('Weekly Tracker'!$N$2:$N$766<>""),'Weekly Tracker'!$N$2:$N$766),"") | L138: =IFERROR(LOOKUP(2,1/('Weekly Tracker'!$E$2:$E$766=$A138)/('Weekly Tracker'!$O$2:$O$766<>""),'Weekly Tracker'!$O$2:$O$766),"")
A139: Abijith Uday Infy | B139: +91 95001 24191 | E139: Tamil Nadu, India | F139: =IFERROR(LOOKUP(2,1/('Weekly Tracker'!$E$2:$E$766=$A139)/('Weekly Tracker'!$F$2:$F$766<>""),'Weekly Tracker'!$F$2:$F$766),"") | G139: =IF(F139<>"",LOOKUP(2,1/('Weekly Tracker'!$E$2:$E$766=$A139)/('Weekly Tracker'!$F$2:$F$766<>""),'Weekly Tracker'!$G$2:$G$766),"") | H139: =IFERROR(LOOKUP(2,1/('Weekly Tracker'!$E$2:$E$766=$A139)/('Weekly Tracker'!$H$2:$H$766<>""),'Weekly Tracker'!$H$2:$H$766),"") | I139: =IF(H139<>"",LOOKUP(2,1/('Weekly Tracker'!$E$2:$E$766=$A139)/('Weekly Tracker'!$H$2:$H$766<>""),'Weekly Tracker'!$I$2:$I$766),"") | J139: =IFERROR(LOOKUP(2,1/('Weekly Tracker'!$E$2:$E$766=$A139)/('Weekly Tracker'!$J$2:$J$766<>""),'Weekly Tracker'!$J$2:$J$766),"") | K139: =IFERROR(LOOKUP(2,1/('Weekly Tracker'!$E$2:$E$766=$A139)/('Weekly Tracker'!$N$2:$N$766<>""),'Weekly Tracker'!$N$2:$N$766),"") | L139: =IFERROR(LOOKUP(2,1/('Weekly Tracker'!$E$2:$E$766=$A139)/('Weekly Tracker'!$O$2:$O$766<>""),'Weekly Tracker'!$O$2:$O$766),"")
A140: Shibi Chakravarthy FB | B140: 919566612326 | F140: =IFERROR(LOOKUP(2,1/('Weekly Tracker'!$E$2:$E$766=$A140)/('Weekly Tracker'!$F$2:$F$766<>""),'Weekly Tracker'!$F$2:$F$766),"") | G140: =IF(F140<>"",LOOKUP(2,1/('Weekly Tracker'!$E$2:$E$766=$A140)/('Weekly Tracker'!$F$2:$F$766<>""),'Weekly Tracker'!$G$2:$G$766),"") | H140: =IFERROR(LOOKUP(2,1/('Weekly Tracker'!$E$2:$E$766=$A140)/('Weekly Tracker'!$H$2:$H$766<>""),'Weekly Tracker'!$H$2:$H$766),"") | I140: =IF(H140<>"",LOOKUP(2,1/('Weekly Tracker'!$E$2:$E$766=$A140)/('Weekly Tracker'!$H$2:$H$766<>""),'Weekly Tracker'!$I$2:$I$766),"") | J140: =IFERROR(LOOKUP(2,1/('Weekly Tracker'!$E$2:$E$766=$A140)/('Weekly Tracker'!$J$2:$J$766<>""),'Weekly Tracker'!$J$2:$J$766),"") | K140: =IFERROR(LOOKUP(2,1/('Weekly Tracker'!$E$2:$E$766=$A140)/('Weekly Tracker'!$N$2:$N$766<>""),'Weekly Tracker'!$N$2:$N$766),"") | L140: =IFERROR(LOOKUP(2,1/('Weekly Tracker'!$E$2:$E$766=$A140)/('Weekly Tracker'!$O$2:$O$766<>""),'Weekly Tracker'!$O$2:$O$766),"")
A141: Distress Number | B141: 112 | F141: =IFERROR(LOOKUP(2,1/('Weekly Tracker'!$E$2:$E$766=$A141)/('Weekly Tracker'!$F$2:$F$766<>""),'Weekly Tracker'!$F$2:$F$766),"") | G141: =IF(F141<>"",LOOKUP(2,1/('Weekly Tracker'!$E$2:$E$766=$A141)/('Weekly Tracker'!$F$2:$F$766<>""),'Weekly Tracker'!$G$2:$G$766),"") | H141: =IFERROR(LOOKUP(2,1/('Weekly Tracker'!$E$2:$E$766=$A141)/('Weekly Tracker'!$H$2:$H$766<>""),'Weekly Tracker'!$H$2:$H$766),"") | I141: =IF(H141<>"",LOOKUP(2,1/('Weekly Tracker'!$E$2:$E$766=$A141)/('Weekly Tracker'!$H$2:$H$766<>""),'Weekly Tracker'!$I$2:$I$766),"") | J141: =IFERROR(LOOKUP(2,1/('Weekly Tracker'!$E$2:$E$766=$A141)/('Weekly Tracker'!$J$2:$J$766<>""),'Weekly Tracker'!$J$2:$J$766),"") | K141: =IFERROR(LOOKUP(2,1/('Weekly Tracker'!$E$2:$E$766=$A141)/('Weekly Tracker'!$N$2:$N$766<>""),'Weekly Tracker'!$N$2:$N$766),"") | L141: =IFERROR(LOOKUP(2,1/('Weekly Tracker'!$E$2:$E$766=$A141)/('Weekly Tracker'!$O$2:$O$766<>""),'Weekly Tracker'!$O$2:$O$766),"")
A142: Padma Akka | B142: 919750383402 | E142: Tamil Nadu, India | F142: =IFERROR(LOOKUP(2,1/('Weekly Tracker'!$E$2:$E$766=$A142)/('Weekly Tracker'!$F$2:$F$766<>""),'Weekly Tracker'!$F$2:$F$766),"") | G142: =IF(F142<>"",LOOKUP(2,1/('Weekly Tracker'!$E$2:$E$766=$A142)/('Weekly Tracker'!$F$2:$F$766<>""),'Weekly Tracker'!$G$2:$G$766),"") | H142: =IFERROR(LOOKUP(2,1/('Weekly Tracker'!$E$2:$E$766=$A142)/('Weekly Tracker'!$H$2:$H$766<>""),'Weekly Tracker'!$H$2:$H$766),"") | I142: =IF(H142<>"",LOOKUP(2,1/('Weekly Tracker'!$E$2:$E$766=$A142)/('Weekly Tracker'!$H$2:$H$766<>""),'Weekly Tracker'!$I$2:$I$766),"") | J142: =IFERROR(LOOKUP(2,1/('Weekly Tracker'!$E$2:$E$766=$A142)/('Weekly Tracker'!$J$2:$J$766<>""),'Weekly Tracker'!$J$2:$J$766),"") | K142: =IFERROR(LOOKUP(2,1/('Weekly Tracker'!$E$2:$E$766=$A142)/('Weekly Tracker'!$N$2:$N$766<>""),'Weekly Tracker'!$N$2:$N$766),"") | L142: =IFERROR(LOOKUP(2,1/('Weekly Tracker'!$E$2:$E$766=$A142)/('Weekly Tracker'!$O$2:$O$766<>""),'Weekly Tracker'!$O$2:$O$766),"")
A143: Abhinav Krishna HCL | B143: 8920244428 | F143: =IFERROR(LOOKUP(2,1/('Weekly Tracker'!$E$2:$E$766=$A143)/('Weekly Tracker'!$F$2:$F$766<>""),'Weekly Tracker'!$F$2:$F$766),"") | G143: =IF(F143<>"",LOOKUP(2,1/('Weekly Tracker'!$E$2:$E$766=$A143)/('Weekly Tracker'!$F$2:$F$766<>""),'Weekly Tracker'!$G$2:$G$766),"") | H143: =IFERROR(LOOKUP(2,1/('Weekly Tracker'!$E$2:$E$766=$A143)/('Weekly Tracker'!$H$2:$H$766<>""),'Weekly Tracker'!$H$2:$H$766),"") | I143: =IF(H143<>"",LOOKUP(2,1/('Weekly Tracker'!$E$2:$E$766=$A143)/('Weekly Tracker'!$H$2:$H$766<>""),'Weekly Tracker'!$I$2:$I$766),"") | J143: =IFERROR(LOOKUP(2,1/('Weekly Tracker'!$E$2:$E$766=$A143)/('Weekly Tracker'!$J$2:$J$766<>""),'Weekly Tracker'!$J$2:$J$766),"") | K143: =IFERROR(LOOKUP(2,1/('Weekly Tracker'!$E$2:$E$766=$A143)/('Weekly Tracker'!$N$2:$N$766<>""),'Weekly Tracker'!$N$2:$N$766),"") | L143: =IFERROR(LOOKUP(2,1/('Weekly Tracker'!$E$2:$E$766=$A143)/('Weekly Tracker'!$O$2:$O$766<>""),'Weekly Tracker'!$O$2:$O$766),"")
A144: Tamil Puli Ford | B144: 919003888430 | F144: =IFERROR(LOOKUP(2,1/('Weekly Tracker'!$E$2:$E$766=$A144)/('Weekly Tracker'!$F$2:$F$766<>""),'Weekly Tracker'!$F$2:$F$766),"") | G144: =IF(F144<>"",LOOKUP(2,1/('Weekly Tracker'!$E$2:$E$766=$A144)/('Weekly Tracker'!$F$2:$F$766<>""),'Weekly Tracker'!$G$2:$G$766),"") | H144: =IFERROR(LOOKUP(2,1/('Weekly Tracker'!$E$2:$E$766=$A144)/('Weekly Tracker'!$H$2:$H$766<>""),'Weekly Tracker'!$H$2:$H$766),"") | I144: =IF(H144<>"",LOOKUP(2,1/('Weekly Tracker'!$E$2:$E$766=$A144)/('Weekly Tracker'!$H$2:$H$766<>""),'Weekly Tracker'!$I$2:$I$766),"") | J144: =IFERROR(LOOKUP(2,1/('Weekly Tracker'!$E$2:$E$766=$A144)/('Weekly Tracker'!$J$2:$J$766<>""),'Weekly Tracker'!$J$2:$J$766),"") | K144: =IFERROR(LOOKUP(2,1/('Weekly Tracker'!$E$2:$E$766=$A144)/('Weekly Tracker'!$N$2:$N$766<>""),'Weekly Tracker'!$N$2:$N$766),"") | L144: =IFERROR(LOOKUP(2,1/('Weekly Tracker'!$E$2:$E$766=$A144)/('Weekly Tracker'!$O$2:$O$766<>""),'Weekly Tracker'!$O$2:$O$766),"")
A145: PuneethAnna | B145: 919677149869 | F145: =IFERROR(LOOKUP(2,1/('Weekly Tracker'!$E$2:$E$766=$A145)/('Weekly Tracker'!$F$2:$F$766<>""),'Weekly Tracker'!$F$2:$F$766),"") | G145: =IF(F145<>"",LOOKUP(2,1/('Weekly Tracker'!$E$2:$E$766=$A145)/('Weekly Tracker'!$F$2:$F$766<>""),'Weekly Tracker'!$G$2:$G$766),"") | H145: =IFERROR(LOOKUP(2,1/('Weekly Tracker'!$E$2:$E$766=$A145)/('Weekly Tracker'!$H$2:$H$766<>""),'Weekly Tracker'!$H$2:$H$766),"") | I145: =IF(H145<>"",LOOKUP(2,1/('Weekly Tracker'!$E$2:$E$766=$A145)/('Weekly Tracker'!$H$2:$H$766<>""),'Weekly Tracker'!$I$2:$I$766),"") | J145: =IFERROR(LOOKUP(2,1/('Weekly Tracker'!$E$2:$E$766=$A145)/('Weekly Tracker'!$J$2:$J$766<>""),'Weekly Tracker'!$J$2:$J$766),"") | K145: =IFERROR(LOOKUP(2,1/('Weekly Tracker'!$E$2:$E$766=$A145)/('Weekly Tracker'!$N$2:$N$766<>""),'Weekly Tracker'!$N$2:$N$766),"") | L145: =IFERROR(LOOKUP(2,1/('Weekly Tracker'!$E$2:$E$766=$A145)/('Weekly Tracker'!$O$2:$O$766<>""),'Weekly Tracker'!$O$2:$O$766),"")
A146: Manoj Kumar Pandiyan HCL | B146: 919677179790 | F146: =IFERROR(LOOKUP(2,1/('Weekly Tracker'!$E$2:$E$766=$A146)/('Weekly Tracker'!$F$2:$F$766<>""),'Weekly Tracker'!$F$2:$F$766),"") | G146: =IF(F146<>"",LOOKUP(2,1/('Weekly Tracker'!$E$2:$E$766=$A146)/('Weekly Tracker'!$F$2:$F$766<>""),'Weekly Tracker'!$G$2:$G$766),"") | H146: =IFERROR(LOOKUP(2,1/('Weekly Tracker'!$E$2:$E$766=$A146)/('Weekly Tracker'!$H$2:$H$766<>""),'Weekly Tracker'!$H$2:$H$766),"") | I146: =IF(H146<>"",LOOKUP(2,1/('Weekly Tracker'!$E$2:$E$766=$A146)/('Weekly Tracker'!$H$2:$H$766<>""),'Weekly Tracker'!$I$2:$I$766),"") | J146: =IFERROR(LOOKUP(2,1/('Weekly Tracker'!$E$2:$E$766=$A146)/('Weekly Tracker'!$J$2:$J$766<>""),'Weekly Tracker'!$J$2:$J$766),"") | K146: =IFERROR(LOOKUP(2,1/('Weekly Tracker'!$E$2:$E$766=$A146)/('Weekly Tracker'!$N$2:$N$766<>""),'Weekly Tracker'!$N$2:$N$766),"") | L146: =IFERROR(LOOKUP(2,1/('Weekly Tracker'!$E$2:$E$766=$A146)/('Weekly Tracker'!$O$2:$O$766<>""),'Weekly Tracker'!$O$2:$O$766),"")
A147: Dhivya Tiruvengadam Urja | B147: 8940103390 | F147: =IFERROR(LOOKUP(2,1/('Weekly Tracker'!$E$2:$E$766=$A147)/('Weekly Tracker'!$F$2:$F$766<>""),'Weekly Tracker'!$F$2:$F$766),"") | G147: =IF(F147<>"",LOOKUP(2,1/('Weekly Tracker'!$E$2:$E$766=$A147)/('Weekly Tracker'!$F$2:$F$766<>""),'Weekly Tracker'!$G$2:$G$766),"") | H147: =IFERROR(LOOKUP(2,1/('Weekly Tracker'!$E$2:$E$766=$A147)/('Weekly Tracker'!$H$2:$H$766<>""),'Weekly Tracker'!$H$2:$H$766),"") | I147: =IF(H147<>"",LOOKUP(2,1/('Weekly Tracker'!$E$2:$E$766=$A147)/('Weekly Tracker'!$H$2:$H$766<>""),'Weekly Tracker'!$I$2:$I$766),"") | J147: =IFERROR(LOOKUP(2,1/('Weekly Tracker'!$E$2:$E$766=$A147)/('Weekly Tracker'!$J$2:$J$766<>""),'Weekly Tracker'!$J$2:$J$766),"") | K147: =IFERROR(LOOKUP(2,1/('Weekly Tracker'!$E$2:$E$766=$A147)/('Weekly Tracker'!$N$2:$N$766<>""),'Weekly Tracker'!$N$2:$N$766),"") | L147: =IFERROR(LOOKUP(2,1/('Weekly Tracker'!$E$2:$E$766=$A147)/('Weekly Tracker'!$O$2:$O$766<>""),'Weekly Tracker'!$O$2:$O$766),"")
A148: Yoganathan Future computer | B148: 919962654947 | F148: =IFERROR(LOOKUP(2,1/('Weekly Tracker'!$E$2:$E$766=$A148)/('Weekly Tracker'!$F$2:$F$766<>""),'Weekly Tracker'!$F$2:$F$766),"") | G148: =IF(F148<>"",LOOKUP(2,1/('Weekly Tracker'!$E$2:$E$766=$A148)/('Weekly Tracker'!$F$2:$F$766<>""),'Weekly Tracker'!$G$2:$G$766),"") | H148: =IFERROR(LOOKUP(2,1/('Weekly Tracker'!$E$2:$E$766=$A148)/('Weekly Tracker'!$H$2:$H$766<>""),'Weekly Tracker'!$H$2:$H$766),"") | I148: =IF(H148<>"",LOOKUP(2,1/('Weekly Tracker'!$E$2:$E$766=$A148)/('Weekly Tracker'!$H$2:$H$766<>""),'Weekly Tracker'!$I$2:$I$766),"") | J148: =IFERROR(LOOKUP(2,1/('Weekly Tracker'!$E$2:$E$766=$A148)/('Weekly Tracker'!$J$2:$J$766<>""),'Weekly Tracker'!$J$2:$J$766),"") | K148: =IFERROR(LOOKUP(2,1/('Weekly Tracker'!$E$2:$E$766=$A148)/('Weekly Tracker'!$N$2:$N$766<>""),'Weekly Tracker'!$N$2:$N$766),"") | L148: =IFERROR(LOOKUP(2,1/('Weekly Tracker'!$E$2:$E$766=$A148)/('Weekly Tracker'!$O$2:$O$766<>""),'Weekly Tracker'!$O$2:$O$766),"")
A149: Rahul Sivaguru Frd | B149: 919962168618 | F149: =IFERROR(LOOKUP(2,1/('Weekly Tracker'!$E$2:$E$766=$A149)/('Weekly Tracker'!$F$2:$F$766<>""),'Weekly Tracker'!$F$2:$F$766),"") | G149: =IF(F149<>"",LOOKUP(2,1/('Weekly Tracker'!$E$2:$E$766=$A149)/('Weekly Tracker'!$F$2:$F$766<>""),'Weekly Tracker'!$G$2:$G$766),"") | H149: =IFERROR(LOOKUP(2,1/('Weekly Tracker'!$E$2:$E$766=$A149)/('Weekly Tracker'!$H$2:$H$766<>""),'Weekly Tracker'!$H$2:$H$766),"") | I149: =IF(H149<>"",LOOKUP(2,1/('Weekly Tracker'!$E$2:$E$766=$A149)/('Weekly Tracker'!$H$2:$H$766<>""),'Weekly Tracker'!$I$2:$I$766),"") | J149: =IFERROR(LOOKUP(2,1/('Weekly Tracker'!$E$2:$E$766=$A149)/('Weekly Tracker'!$J$2:$J$766<>""),'Weekly Tracker'!$J$2:$J$766),"") | K149: =IFERROR(LOOKUP(2,1/('Weekly Tracker'!$E$2:$E$766=$A149)/('Weekly Tracker'!$N$2:$N$766<>""),'Weekly Tracker'!$N$2:$N$766),"") | L149: =IFERROR(LOOKUP(2,1/('Weekly Tracker'!$E$2:$E$766=$A149)/('Weekly Tracker'!$O$2:$O$766<>""),'Weekly Tracker'!$O$2:$O$766),"")
A150: Venkatesh P Scl | B150: 917502740608 | F150: =IFERROR(LOOKUP(2,1/('Weekly Tracker'!$E$2:$E$766=$A150)/('Weekly Tracker'!$F$2:$F$766<>""),'Weekly Tracker'!$F$2:$F$766),"") | G150: =IF(F150<>"",LOOKUP(2,1/('Weekly Tracker'!$E$2:$E$766=$A150)/('Weekly Tracker'!$F$2:$F$766<>""),'Weekly Tracker'!$G$2:$G$766),"") | H150: =IFERROR(LOOKUP(2,1/('Weekly Tracker'!$E$2:$E$766=$A150)/('Weekly Tracker'!$H$2:$H$766<>""),'Weekly Tracker'!$H$2:$H$766),"") | I150: =IF(H150<>"",LOOKUP(2,1/('Weekly Tracker'!$E$2:$E$766=$A150)/('Weekly Tracker'!$H$2:$H$766<>""),'Weekly Tracker'!$I$2:$I$766),"") | J150: =IFERROR(LOOKUP(2,1/('Weekly Tracker'!$E$2:$E$766=$A150)/('Weekly Tracker'!$J$2:$J$766<>""),'Weekly Tracker'!$J$2:$J$766),"") | K150: =IFERROR(LOOKUP(2,1/('Weekly Tracker'!$E$2:$E$766=$A150)/('Weekly Tracker'!$N$2:$N$766<>""),'Weekly Tracker'!$N$2:$N$766),"") | L150: =IFERROR(LOOKUP(2,1/('Weekly Tracker'!$E$2:$E$766=$A150)/('Weekly Tracker'!$O$2:$O$766<>""),'Weekly Tracker'!$O$2:$O$766),"")
A151: Supriya Akshya | B151: 918754289523 | F151: =IFERROR(LOOKUP(2,1/('Weekly Tracker'!$E$2:$E$766=$A151)/('Weekly Tracker'!$F$2:$F$766<>""),'Weekly Tracker'!$F$2:$F$766),"") | G151: =IF(F151<>"",LOOKUP(2,1/('Weekly Tracker'!$E$2:$E$766=$A151)/('Weekly Tracker'!$F$2:$F$766<>""),'Weekly Tracker'!$G$2:$G$766),"") | H151: =IFERROR(LOOKUP(2,1/('Weekly Tracker'!$E$2:$E$766=$A151)/('Weekly Tracker'!$H$2:$H$766<>""),'Weekly Tracker'!$H$2:$H$766),"") | I151: =IF(H151<>"",LOOKUP(2,1/('Weekly Tracker'!$E$2:$E$766=$A151)/('Weekly Tracker'!$H$2:$H$766<>""),'Weekly Tracker'!$I$2:$I$766),"") | J151: =IFERROR(LOOKUP(2,1/('Weekly Tracker'!$E$2:$E$766=$A151)/('Weekly Tracker'!$J$2:$J$766<>""),'Weekly Tracker'!$J$2:$J$766),"") | K151: =IFERROR(LOOKUP(2,1/('Weekly Tracker'!$E$2:$E$766=$A151)/('Weekly Tracker'!$N$2:$N$766<>""),'Weekly Tracker'!$N$2:$N$766),"") | L151: =IFERROR(LOOKUP(2,1/('Weekly Tracker'!$E$2:$E$766=$A151)/('Weekly Tracker'!$O$2:$O$766<>""),'Weekly Tracker'!$O$2:$O$766),"")
A152: Sundar G FB | B152: 9566372105 | F152: =IFERROR(LOOKUP(2,1/('Weekly Tracker'!$E$2:$E$766=$A152)/('Weekly Tracker'!$F$2:$F$766<>""),'Weekly Tracker'!$F$2:$F$766),"") | G152: =IF(F152<>"",LOOKUP(2,1/('Weekly Tracker'!$E$2:$E$766=$A152)/('Weekly Tracker'!$F$2:$F$766<>""),'Weekly Tracker'!$G$2:$G$766),"") | H152: =IFERROR(LOOKUP(2,1/('Weekly Tracker'!$E$2:$E$766=$A152)/('Weekly Tracker'!$H$2:$H$766<>""),'Weekly Tracker'!$H$2:$H$766),"") | I152: =IF(H152<>"",LOOKUP(2,1/('Weekly Tracker'!$E$2:$E$766=$A152)/('Weekly Tracker'!$H$2:$H$766<>""),'Weekly Tracker'!$I$2:$I$766),"") | J152: =IFERROR(LOOKUP(2,1/('Weekly Tracker'!$E$2:$E$766=$A152)/('Weekly Tracker'!$J$2:$J$766<>""),'Weekly Tracker'!$J$2:$J$766),"") | K152: =IFERROR(LOOKUP(2,1/('Weekly Tracker'!$E$2:$E$766=$A152)/('Weekly Tracker'!$N$2:$N$766<>""),'Weekly Tracker'!$N$2:$N$766),"") | L152: =IFERROR(LOOKUP(2,1/('Weekly Tracker'!$E$2:$E$766=$A152)/('Weekly Tracker'!$O$2:$O$766<>""),'Weekly Tracker'!$O$2:$O$766),"")
A153: Vishal Rapido | B153: 7550274263 | F153: =IFERROR(LOOKUP(2,1/('Weekly Tracker'!$E$2:$E$766=$A153)/('Weekly Tracker'!$F$2:$F$766<>""),'Weekly Tracker'!$F$2:$F$766),"") | G153: =IF(F153<>"",LOOKUP(2,1/('Weekly Tracker'!$E$2:$E$766=$A153)/('Weekly Tracker'!$F$2:$F$766<>""),'Weekly Tracker'!$G$2:$G$766),"") | H153: =IFERROR(LOOKUP(2,1/('Weekly Tracker'!$E$2:$E$766=$A153)/('Weekly Tracker'!$H$2:$H$766<>""),'Weekly Tracker'!$H$2:$H$766),"") | I153: =IF(H153<>"",LOOKUP(2,1/('Weekly Tracker'!$E$2:$E$766=$A153)/('Weekly Tracker'!$H$2:$H$766<>""),'Weekly Tracker'!$I$2:$I$766),"") | J153: =IFERROR(LOOKUP(2,1/('Weekly Tracker'!$E$2:$E$766=$A153)/('Weekly Tracker'!$J$2:$J$766<>""),'Weekly Tracker'!$J$2:$J$766),"") | K153: =IFERROR(LOOKUP(2,1/('Weekly Tracker'!$E$2:$E$766=$A153)/('Weekly Tracker'!$N$2:$N$766<>""),'Weekly Tracker'!$N$2:$N$766),"") | L153: =IFERROR(LOOKUP(2,1/('Weekly Tracker'!$E$2:$E$766=$A153)/('Weekly Tracker'!$O$2:$O$766<>""),'Weekly Tracker'!$O$2:$O$766),"")
A154: Madhan Paulsamy Urja | B154: 919042409040 | F154: =IFERROR(LOOKUP(2,1/('Weekly Tracker'!$E$2:$E$766=$A154)/('Weekly Tracker'!$F$2:$F$766<>""),'Weekly Tracker'!$F$2:$F$766),"") | G154: =IF(F154<>"",LOOKUP(2,1/('Weekly Tracker'!$E$2:$E$766=$A154)/('Weekly Tracker'!$F$2:$F$766<>""),'Weekly Tracker'!$G$2:$G$766),"") | H154: =IFERROR(LOOKUP(2,1/('Weekly Tracker'!$E$2:$E$766=$A154)/('Weekly Tracker'!$H$2:$H$766<>""),'Weekly Tracker'!$H$2:$H$766),"") | I154: =IF(H154<>"",LOOKUP(2,1/('Weekly Tracker'!$E$2:$E$766=$A154)/('Weekly Tracker'!$H$2:$H$766<>""),'Weekly Tracker'!$I$2:$I$766),"") | J154: =IFERROR(LOOKUP(2,1/('Weekly Tracker'!$E$2:$E$766=$A154)/('Weekly Tracker'!$J$2:$J$766<>""),'Weekly Tracker'!$J$2:$J$766),"") | K154: =IFERROR(LOOKUP(2,1/('Weekly Tracker'!$E$2:$E$766=$A154)/('Weekly Tracker'!$N$2:$N$766<>""),'Weekly Tracker'!$N$2:$N$766),"") | L154: =IFERROR(LOOKUP(2,1/('Weekly Tracker'!$E$2:$E$766=$A154)/('Weekly Tracker'!$O$2:$O$766<>""),'Weekly Tracker'!$O$2:$O$766),"")
A155: AAAAmma | B155: +91 93849 01309, 919488301309 | F155: =IFERROR(LOOKUP(2,1/('Weekly Tracker'!$E$2:$E$766=$A155)/('Weekly Tracker'!$F$2:$F$766<>""),'Weekly Tracker'!$F$2:$F$766),"") | G155: =IF(F155<>"",LOOKUP(2,1/('Weekly Tracker'!$E$2:$E$766=$A155)/('Weekly Tracker'!$F$2:$F$766<>""),'Weekly Tracker'!$G$2:$G$766),"") | H155: =IFERROR(LOOKUP(2,1/('Weekly Tracker'!$E$2:$E$766=$A155)/('Weekly Tracker'!$H$2:$H$766<>""),'Weekly Tracker'!$H$2:$H$766),"") | I155: =IF(H155<>"",LOOKUP(2,1/('Weekly Tracker'!$E$2:$E$766=$A155)/('Weekly Tracker'!$H$2:$H$766<>""),'Weekly Tracker'!$I$2:$I$766),"") | J155: =IFERROR(LOOKUP(2,1/('Weekly Tracker'!$E$2:$E$766=$A155)/('Weekly Tracker'!$J$2:$J$766<>""),'Weekly Tracker'!$J$2:$J$766),"") | K155: =IFERROR(LOOKUP(2,1/('Weekly Tracker'!$E$2:$E$766=$A155)/('Weekly Tracker'!$N$2:$N$766<>""),'Weekly Tracker'!$N$2:$N$766),"") | L155: =IFERROR(LOOKUP(2,1/('Weekly Tracker'!$E$2:$E$766=$A155)/('Weekly Tracker'!$O$2:$O$766<>""),'Weekly Tracker'!$O$2:$O$766),"")
A156: Kanchana | B156: 919087165195 | E156: Tamil Nadu, India | F156: =IFERROR(LOOKUP(2,1/('Weekly Tracker'!$E$2:$E$766=$A156)/('Weekly Tracker'!$F$2:$F$766<>""),'Weekly Tracker'!$F$2:$F$766),"") | G156: =IF(F156<>"",LOOKUP(2,1/('Weekly Tracker'!$E$2:$E$766=$A156)/('Weekly Tracker'!$F$2:$F$766<>""),'Weekly Tracker'!$G$2:$G$766),"") | H156: =IFERROR(LOOKUP(2,1/('Weekly Tracker'!$E$2:$E$766=$A156)/('Weekly Tracker'!$H$2:$H$766<>""),'Weekly Tracker'!$H$2:$H$766),"") | I156: =IF(H156<>"",LOOKUP(2,1/('Weekly Tracker'!$E$2:$E$766=$A156)/('Weekly Tracker'!$H$2:$H$766<>""),'Weekly Tracker'!$I$2:$I$766),"") | J156: =IFERROR(LOOKUP(2,1/('Weekly Tracker'!$E$2:$E$766=$A156)/('Weekly Tracker'!$J$2:$J$766<>""),'Weekly Tracker'!$J$2:$J$766),"") | K156: =IFERROR(LOOKUP(2,1/('Weekly Tracker'!$E$2:$E$766=$A156)/('Weekly Tracker'!$N$2:$N$766<>""),'Weekly Tracker'!$N$2:$N$766),"") | L156: =IFERROR(LOOKUP(2,1/('Weekly Tracker'!$E$2:$E$766=$A156)/('Weekly Tracker'!$O$2:$O$766<>""),'Weekly Tracker'!$O$2:$O$766),"")
A157: Shankar M FB | B157: 9940886744 | F157: =IFERROR(LOOKUP(2,1/('Weekly Tracker'!$E$2:$E$766=$A157)/('Weekly Tracker'!$F$2:$F$766<>""),'Weekly Tracker'!$F$2:$F$766),"") | G157: =IF(F157<>"",LOOKUP(2,1/('Weekly Tracker'!$E$2:$E$766=$A157)/('Weekly Tracker'!$F$2:$F$766<>""),'Weekly Tracker'!$G$2:$G$766),"") | H157: =IFERROR(LOOKUP(2,1/('Weekly Tracker'!$E$2:$E$766=$A157)/('Weekly Tracker'!$H$2:$H$766<>""),'Weekly Tracker'!$H$2:$H$766),"") | I157: =IF(H157<>"",LOOKUP(2,1/('Weekly Tracker'!$E$2:$E$766=$A157)/('Weekly Tracker'!$H$2:$H$766<>""),'Weekly Tracker'!$I$2:$I$766),"") | J157: =IFERROR(LOOKUP(2,1/('Weekly Tracker'!$E$2:$E$766=$A157)/('Weekly Tracker'!$J$2:$J$766<>""),'Weekly Tracker'!$J$2:$J$766),"") | K157: =IFERROR(LOOKUP(2,1/('Weekly Tracker'!$E$2:$E$766=$A157)/('Weekly Tracker'!$N$2:$N$766<>""),'Weekly Tracker'!$N$2:$N$766),"") | L157: =IFERROR(LOOKUP(2,1/('Weekly Tracker'!$E$2:$E$766=$A157)/('Weekly Tracker'!$O$2:$O$766<>""),'Weekly Tracker'!$O$2:$O$766),"")
A158: Nishanthi Tshirt | B158: 918124637999 | F158: =IFERROR(LOOKUP(2,1/('Weekly Tracker'!$E$2:$E$766=$A158)/('Weekly Tracker'!$F$2:$F$766<>""),'Weekly Tracker'!$F$2:$F$766),"") | G158: =IF(F158<>"",LOOKUP(2,1/('Weekly Tracker'!$E$2:$E$766=$A158)/('Weekly Tracker'!$F$2:$F$766<>""),'Weekly Tracker'!$G$2:$G$766),"") | H158: =IFERROR(LOOKUP(2,1/('Weekly Tracker'!$E$2:$E$766=$A158)/('Weekly Tracker'!$H$2:$H$766<>""),'Weekly Tracker'!$H$2:$H$766),"") | I158: =IF(H158<>"",LOOKUP(2,1/('Weekly Tracker'!$E$2:$E$766=$A158)/('Weekly Tracker'!$H$2:$H$766<>""),'Weekly Tracker'!$I$2:$I$766),"") | J158: =IFERROR(LOOKUP(2,1/('Weekly Tracker'!$E$2:$E$766=$A158)/('Weekly Tracker'!$J$2:$J$766<>""),'Weekly Tracker'!$J$2:$J$766),"") | K158: =IFERROR(LOOKUP(2,1/('Weekly Tracker'!$E$2:$E$766=$A158)/('Weekly Tracker'!$N$2:$N$766<>""),'Weekly Tracker'!$N$2:$N$766),"") | L158: =IFERROR(LOOKUP(2,1/('Weekly Tracker'!$E$2:$E$766=$A158)/('Weekly Tracker'!$O$2:$O$766<>""),'Weekly Tracker'!$O$2:$O$766),"")
A159: Mrineeth Verz | B159: 919704907087 | F159: =IFERROR(LOOKUP(2,1/('Weekly Tracker'!$E$2:$E$766=$A159)/('Weekly Tracker'!$F$2:$F$766<>""),'Weekly Tracker'!$F$2:$F$766),"") | G159: =IF(F159<>"",LOOKUP(2,1/('Weekly Tracker'!$E$2:$E$766=$A159)/('Weekly Tracker'!$F$2:$F$766<>""),'Weekly Tracker'!$G$2:$G$766),"") | H159: =IFERROR(LOOKUP(2,1/('Weekly Tracker'!$E$2:$E$766=$A159)/('Weekly Tracker'!$H$2:$H$766<>""),'Weekly Tracker'!$H$2:$H$766),"") | I159: =IF(H159<>"",LOOKUP(2,1/('Weekly Tracker'!$E$2:$E$766=$A159)/('Weekly Tracker'!$H$2:$H$766<>""),'Weekly Tracker'!$I$2:$I$766),"") | J159: =IFERROR(LOOKUP(2,1/('Weekly Tracker'!$E$2:$E$766=$A159)/('Weekly Tracker'!$J$2:$J$766<>""),'Weekly Tracker'!$J$2:$J$766),"") | K159: =IFERROR(LOOKUP(2,1/('Weekly Tracker'!$E$2:$E$766=$A159)/('Weekly Tracker'!$N$2:$N$766<>""),'Weekly Tracker'!$N$2:$N$766),"") | L159: =IFERROR(LOOKUP(2,1/('Weekly Tracker'!$E$2:$E$766=$A159)/('Weekly Tracker'!$O$2:$O$766<>""),'Weekly Tracker'!$O$2:$O$766),"")
A160: Udhaya Grp Ucen | B160: 919789537223 | F160: =IFERROR(LOOKUP(2,1/('Weekly Tracker'!$E$2:$E$766=$A160)/('Weekly Tracker'!$F$2:$F$766<>""),'Weekly Tracker'!$F$2:$F$766),"") | G160: =IF(F160<>"",LOOKUP(2,1/('Weekly Tracker'!$E$2:$E$766=$A160)/('Weekly Tracker'!$F$2:$F$766<>""),'Weekly Tracker'!$G$2:$G$766),"") | H160: =IFERROR(LOOKUP(2,1/('Weekly Tracker'!$E$2:$E$766=$A160)/('Weekly Tracker'!$H$2:$H$766<>""),'Weekly Tracker'!$H$2:$H$766),"") | I160: =IF(H160<>"",LOOKUP(2,1/('Weekly Tracker'!$E$2:$E$766=$A160)/('Weekly Tracker'!$H$2:$H$766<>""),'Weekly Tracker'!$I$2:$I$766),"") | J160: =IFERROR(LOOKUP(2,1/('Weekly Tracker'!$E$2:$E$766=$A160)/('Weekly Tracker'!$J$2:$J$766<>""),'Weekly Tracker'!$J$2:$J$766),"") | K160: =IFERROR(LOOKUP(2,1/('Weekly Tracker'!$E$2:$E$766=$A160)/('Weekly Tracker'!$N$2:$N$766<>""),'Weekly Tracker'!$N$2:$N$766),"") | L160: =IFERROR(LOOKUP(2,1/('Weekly Tracker'!$E$2:$E$766=$A160)/('Weekly Tracker'!$O$2:$O$766<>""),'Weekly Tracker'!$O$2:$O$766),"")
A161: Sumathi Neelakandan Mech | B161: 7598838899 | F161: =IFERROR(LOOKUP(2,1/('Weekly Tracker'!$E$2:$E$766=$A161)/('Weekly Tracker'!$F$2:$F$766<>""),'Weekly Tracker'!$F$2:$F$766),"") | G161: =IF(F161<>"",LOOKUP(2,1/('Weekly Tracker'!$E$2:$E$766=$A161)/('Weekly Tracker'!$F$2:$F$766<>""),'Weekly Tracker'!$G$2:$G$766),"") | H161: =IFERROR(LOOKUP(2,1/('Weekly Tracker'!$E$2:$E$766=$A161)/('Weekly Tracker'!$H$2:$H$766<>""),'Weekly Tracker'!$H$2:$H$766),"") | I161: =IF(H161<>"",LOOKUP(2,1/('Weekly Tracker'!$E$2:$E$766=$A161)/('Weekly Tracker'!$H$2:$H$766<>""),'Weekly Tracker'!$I$2:$I$766),"") | J161: =IFERROR(LOOKUP(2,1/('Weekly Tracker'!$E$2:$E$766=$A161)/('Weekly Tracker'!$J$2:$J$766<>""),'Weekly Tracker'!$J$2:$J$766),"") | K161: =IFERROR(LOOKUP(2,1/('Weekly Tracker'!$E$2:$E$766=$A161)/('Weekly Tracker'!$N$2:$N$766<>""),'Weekly Tracker'!$N$2:$N$766),"") | L161: =IFERROR(LOOKUP(2,1/('Weekly Tracker'!$E$2:$E$766=$A161)/('Weekly Tracker'!$O$2:$O$766<>""),'Weekly Tracker'!$O$2:$O$766),"")
A162: Chitra DB Urja | B162: 918056057279 | F162: =IFERROR(LOOKUP(2,1/('Weekly Tracker'!$E$2:$E$766=$A162)/('Weekly Tracker'!$F$2:$F$766<>""),'Weekly Tracker'!$F$2:$F$766),"") | G162: =IF(F162<>"",LOOKUP(2,1/('Weekly Tracker'!$E$2:$E$766=$A162)/('Weekly Tracker'!$F$2:$F$766<>""),'Weekly Tracker'!$G$2:$G$766),"") | H162: =IFERROR(LOOKUP(2,1/('Weekly Tracker'!$E$2:$E$766=$A162)/('Weekly Tracker'!$H$2:$H$766<>""),'Weekly Tracker'!$H$2:$H$766),"") | I162: =IF(H162<>"",LOOKUP(2,1/('Weekly Tracker'!$E$2:$E$766=$A162)/('Weekly Tracker'!$H$2:$H$766<>""),'Weekly Tracker'!$I$2:$I$766),"") | J162: =IFERROR(LOOKUP(2,1/('Weekly Tracker'!$E$2:$E$766=$A162)/('Weekly Tracker'!$J$2:$J$766<>""),'Weekly Tracker'!$J$2:$J$766),"") | K162: =IFERROR(LOOKUP(2,1/('Weekly Tracker'!$E$2:$E$766=$A162)/('Weekly Tracker'!$N$2:$N$766<>""),'Weekly Tracker'!$N$2:$N$766),"") | L162: =IFERROR(LOOKUP(2,1/('Weekly Tracker'!$E$2:$E$766=$A162)/('Weekly Tracker'!$O$2:$O$766<>""),'Weekly Tracker'!$O$2:$O$766),"")
A163: Satheesh Urja | B163: +91 97896 83959 | F163: =IFERROR(LOOKUP(2,1/('Weekly Tracker'!$E$2:$E$766=$A163)/('Weekly Tracker'!$F$2:$F$766<>""),'Weekly Tracker'!$F$2:$F$766),"") | G163: =IF(F163<>"",LOOKUP(2,1/('Weekly Tracker'!$E$2:$E$766=$A163)/('Weekly Tracker'!$F$2:$F$766<>""),'Weekly Tracker'!$G$2:$G$766),"") | H163: =IFERROR(LOOKUP(2,1/('Weekly Tracker'!$E$2:$E$766=$A163)/('Weekly Tracker'!$H$2:$H$766<>""),'Weekly Tracker'!$H$2:$H$766),"") | I163: =IF(H163<>"",LOOKUP(2,1/('Weekly Tracker'!$E$2:$E$766=$A163)/('Weekly Tracker'!$H$2:$H$766<>""),'Weekly Tracker'!$I$2:$I$766),"") | J163: =IFERROR(LOOKUP(2,1/('Weekly Tracker'!$E$2:$E$766=$A163)/('Weekly Tracker'!$J$2:$J$766<>""),'Weekly Tracker'!$J$2:$J$766),"") | K163: =IFERROR(LOOKUP(2,1/('Weekly Tracker'!$E$2:$E$766=$A163)/('Weekly Tracker'!$N$2:$N$766<>""),'Weekly Tracker'!$N$2:$N$766),"") | L163: =IFERROR(LOOKUP(2,1/('Weekly Tracker'!$E$2:$E$766=$A163)/('Weekly Tracker'!$O$2:$O$766<>""),'Weekly Tracker'!$O$2:$O$766),"")
A164: Bhava Urja | B164: 919789789243 | F164: =IFERROR(LOOKUP(2,1/('Weekly Tracker'!$E$2:$E$766=$A164)/('Weekly Tracker'!$F$2:$F$766<>""),'Weekly Tracker'!$F$2:$F$766),"") | G164: =IF(F164<>"",LOOKUP(2,1/('Weekly Tracker'!$E$2:$E$766=$A164)/('Weekly Tracker'!$F$2:$F$766<>""),'Weekly Tracker'!$G$2:$G$766),"") | H164: =IFERROR(LOOKUP(2,1/('Weekly Tracker'!$E$2:$E$766=$A164)/('Weekly Tracker'!$H$2:$H$766<>""),'Weekly Tracker'!$H$2:$H$766),"") | I164: =IF(H164<>"",LOOKUP(2,1/('Weekly Tracker'!$E$2:$E$766=$A164)/('Weekly Tracker'!$H$2:$H$766<>""),'Weekly Tracker'!$I$2:$I$766),"") | J164: =IFERROR(LOOKUP(2,1/('Weekly Tracker'!$E$2:$E$766=$A164)/('Weekly Tracker'!$J$2:$J$766<>""),'Weekly Tracker'!$J$2:$J$766),"") | K164: =IFERROR(LOOKUP(2,1/('Weekly Tracker'!$E$2:$E$766=$A164)/('Weekly Tracker'!$N$2:$N$766<>""),'Weekly Tracker'!$N$2:$N$766),"") | L164: =IFERROR(LOOKUP(2,1/('Weekly Tracker'!$E$2:$E$766=$A164)/('Weekly Tracker'!$O$2:$O$766<>""),'Weekly Tracker'!$O$2:$O$766),"")
A165: Dhinesh Vicky FB | B165: 919942245801 | F165: =IFERROR(LOOKUP(2,1/('Weekly Tracker'!$E$2:$E$766=$A165)/('Weekly Tracker'!$F$2:$F$766<>""),'Weekly Tracker'!$F$2:$F$766),"") | G165: =IF(F165<>"",LOOKUP(2,1/('Weekly Tracker'!$E$2:$E$766=$A165)/('Weekly Tracker'!$F$2:$F$766<>""),'Weekly Tracker'!$G$2:$G$766),"") | H165: =IFERROR(LOOKUP(2,1/('Weekly Tracker'!$E$2:$E$766=$A165)/('Weekly Tracker'!$H$2:$H$766<>""),'Weekly Tracker'!$H$2:$H$766),"") | I165: =IF(H165<>"",LOOKUP(2,1/('Weekly Tracker'!$E$2:$E$766=$A165)/('Weekly Tracker'!$H$2:$H$766<>""),'Weekly Tracker'!$I$2:$I$766),"") | J165: =IFERROR(LOOKUP(2,1/('Weekly Tracker'!$E$2:$E$766=$A165)/('Weekly Tracker'!$J$2:$J$766<>""),'Weekly Tracker'!$J$2:$J$766),"") | K165: =IFERROR(LOOKUP(2,1/('Weekly Tracker'!$E$2:$E$766=$A165)/('Weekly Tracker'!$N$2:$N$766<>""),'Weekly Tracker'!$N$2:$N$766),"") | L165: =IFERROR(LOOKUP(2,1/('Weekly Tracker'!$E$2:$E$766=$A165)/('Weekly Tracker'!$O$2:$O$766<>""),'Weekly Tracker'!$O$2:$O$766),"")
A166: Imran | B166: 917871228301 | F166: =IFERROR(LOOKUP(2,1/('Weekly Tracker'!$E$2:$E$766=$A166)/('Weekly Tracker'!$F$2:$F$766<>""),'Weekly Tracker'!$F$2:$F$766),"") | G166: =IF(F166<>"",LOOKUP(2,1/('Weekly Tracker'!$E$2:$E$766=$A166)/('Weekly Tracker'!$F$2:$F$766<>""),'Weekly Tracker'!$G$2:$G$766),"") | H166: =IFERROR(LOOKUP(2,1/('Weekly Tracker'!$E$2:$E$766=$A166)/('Weekly Tracker'!$H$2:$H$766<>""),'Weekly Tracker'!$H$2:$H$766),"") | I166: =IF(H166<>"",LOOKUP(2,1/('Weekly Tracker'!$E$2:$E$766=$A166)/('Weekly Tracker'!$H$2:$H$766<>""),'Weekly Tracker'!$I$2:$I$766),"") | J166: =IFERROR(LOOKUP(2,1/('Weekly Tracker'!$E$2:$E$766=$A166)/('Weekly Tracker'!$J$2:$J$766<>""),'Weekly Tracker'!$J$2:$J$766),"") | K166: =IFERROR(LOOKUP(2,1/('Weekly Tracker'!$E$2:$E$766=$A166)/('Weekly Tracker'!$N$2:$N$766<>""),'Weekly Tracker'!$N$2:$N$766),"") | L166: =IFERROR(LOOKUP(2,1/('Weekly Tracker'!$E$2:$E$766=$A166)/('Weekly Tracker'!$O$2:$O$766<>""),'Weekly Tracker'!$O$2:$O$766),"")
A167: Sathiesh kumar ACT | B167: 919566084182 | F167: =IFERROR(LOOKUP(2,1/('Weekly Tracker'!$E$2:$E$766=$A167)/('Weekly Tracker'!$F$2:$F$766<>""),'Weekly Tracker'!$F$2:$F$766),"") | G167: =IF(F167<>"",LOOKUP(2,1/('Weekly Tracker'!$E$2:$E$766=$A167)/('Weekly Tracker'!$F$2:$F$766<>""),'Weekly Tracker'!$G$2:$G$766),"") | H167: =IFERROR(LOOKUP(2,1/('Weekly Tracker'!$E$2:$E$766=$A167)/('Weekly Tracker'!$H$2:$H$766<>""),'Weekly Tracker'!$H$2:$H$766),"") | I167: =IF(H167<>"",LOOKUP(2,1/('Weekly Tracker'!$E$2:$E$766=$A167)/('Weekly Tracker'!$H$2:$H$766<>""),'Weekly Tracker'!$I$2:$I$766),"") | J167: =IFERROR(LOOKUP(2,1/('Weekly Tracker'!$E$2:$E$766=$A167)/('Weekly Tracker'!$J$2:$J$766<>""),'Weekly Tracker'!$J$2:$J$766),"") | K167: =IFERROR(LOOKUP(2,1/('Weekly Tracker'!$E$2:$E$766=$A167)/('Weekly Tracker'!$N$2:$N$766<>""),'Weekly Tracker'!$N$2:$N$766),"") | L167: =IFERROR(LOOKUP(2,1/('Weekly Tracker'!$E$2:$E$766=$A167)/('Weekly Tracker'!$O$2:$O$766<>""),'Weekly Tracker'!$O$2:$O$766),"")
A168: Idea Hot Offer | B168: *147*99 | F168: =IFERROR(LOOKUP(2,1/('Weekly Tracker'!$E$2:$E$766=$A168)/('Weekly Tracker'!$F$2:$F$766<>""),'Weekly Tracker'!$F$2:$F$766),"") | G168: =IF(F168<>"",LOOKUP(2,1/('Weekly Tracker'!$E$2:$E$766=$A168)/('Weekly Tracker'!$F$2:$F$766<>""),'Weekly Tracker'!$G$2:$G$766),"") | H168: =IFERROR(LOOKUP(2,1/('Weekly Tracker'!$E$2:$E$766=$A168)/('Weekly Tracker'!$H$2:$H$766<>""),'Weekly Tracker'!$H$2:$H$766),"") | I168: =IF(H168<>"",LOOKUP(2,1/('Weekly Tracker'!$E$2:$E$766=$A168)/('Weekly Tracker'!$H$2:$H$766<>""),'Weekly Tracker'!$I$2:$I$766),"") | J168: =IFERROR(LOOKUP(2,1/('Weekly Tracker'!$E$2:$E$766=$A168)/('Weekly Tracker'!$J$2:$J$766<>""),'Weekly Tracker'!$J$2:$J$766),"") | K168: =IFERROR(LOOKUP(2,1/('Weekly Tracker'!$E$2:$E$766=$A168)/('Weekly Tracker'!$N$2:$N$766<>""),'Weekly Tracker'!$N$2:$N$766),"") | L168: =IFERROR(LOOKUP(2,1/('Weekly Tracker'!$E$2:$E$766=$A168)/('Weekly Tracker'!$O$2:$O$766<>""),'Weekly Tracker'!$O$2:$O$766),"")
... A213: Nidhun balaji Grp Ucen | B213: 919487002651 | F213: =IFERROR(LOOKUP(2,1/('Weekly Tracker'!$E$2:$E$766=$A213)/('Weekly Tracker'!$F$2:$F$766<>""),'Weekly Tracker'!$F$2:$F$766),"") | G213: =IF(F213<>"",LOOKUP(2,1/('Weekly Tracker'!$E$2:$E$766=$A213)/('Weekly Tracker'!$F$2:$F$766<>""),'Weekly Tracker'!$G$2:$G$766),"") | H213: =IFERROR(LOOKUP(2,1/('Weekly Tracker'!$E$2:$E$766=$A213)/('Weekly Tracker'!$H$2:$H$766<>""),'Weekly Tracker'!$H$2:$H$766),"") | I213: =IF(H213<>"",LOOKUP(2,1/('Weekly Tracker'!$E$2:$E$766=$A213)/('Weekly Tracker'!$H$2:$H$766<>""),'Weekly Tracker'!$I$2:$I$766),"") | J213: =IFERROR(LOOKUP(2,1/('Weekly Tracker'!$E$2:$E$766=$A213)/('Weekly Tracker'!$J$2:$J$766<>""),'Weekly Tracker'!$J$2:$J$766),"") | K213: =IFERROR(LOOKUP(2,1/('Weekly Tracker'!$E$2:$E$766=$A213)/('Weekly Tracker'!$N$2:$N$766<>""),'Weekly Tracker'!$N$2:$N$766),"") | L213: =IFERROR(LOOKUP(2,1/('Weekly Tracker'!$E$2:$E$766=$A213)/('Weekly Tracker'!$O$2:$O$766<>""),'Weekly Tracker'!$O$2:$O$766),"")
A214: Sadagopan Sangeetha | B214: 919884146973 | E214: Chennai, India | F214: =IFERROR(LOOKUP(2,1/('Weekly Tracker'!$E$2:$E$766=$A214)/('Weekly Tracker'!$F$2:$F$766<>""),'Weekly Tracker'!$F$2:$F$766),"") | G214: =IF(F214<>"",LOOKUP(2,1/('Weekly Tracker'!$E$2:$E$766=$A214)/('Weekly Tracker'!$F$2:$F$766<>""),'Weekly Tracker'!$G$2:$G$766),"") | H214: =IFERROR(LOOKUP(2,1/('Weekly Tracker'!$E$2:$E$766=$A214)/('Weekly Tracker'!$H$2:$H$766<>""),'Weekly Tracker'!$H$2:$H$766),"") | I214: =IF(H214<>"",LOOKUP(2,1/('Weekly Tracker'!$E$2:$E$766=$A214)/('Weekly Tracker'!$H$2:$H$766<>""),'Weekly Tracker'!$I$2:$I$766),"") | J214: =IFERROR(LOOKUP(2,1/('Weekly Tracker'!$E$2:$E$766=$A214)/('Weekly Tracker'!$J$2:$J$766<>""),'Weekly Tracker'!$J$2:$J$766),"") | K214: =IFERROR(LOOKUP(2,1/('Weekly Tracker'!$E$2:$E$766=$A214)/('Weekly Tracker'!$N$2:$N$766<>""),'Weekly Tracker'!$N$2:$N$766),"") | L214: =IFERROR(LOOKUP(2,1/('Weekly Tracker'!$E$2:$E$766=$A214)/('Weekly Tracker'!$O$2:$O$766<>""),'Weekly Tracker'!$O$2:$O$766),"")
A215: Mari Raj Civil | B215: 919095826287 | F215: =IFERROR(LOOKUP(2,1/('Weekly Tracker'!$E$2:$E$766=$A215)/('Weekly Tracker'!$F$2:$F$766<>""),'Weekly Tracker'!$F$2:$F$766),"") | G215: =IF(F215<>"",LOOKUP(2,1/('Weekly Tracker'!$E$2:$E$766=$A215)/('Weekly Tracker'!$F$2:$F$766<>""),'Weekly Tracker'!$G$2:$G$766),"") | H215: =IFERROR(LOOKUP(2,1/('Weekly Tracker'!$E$2:$E$766=$A215)/('Weekly Tracker'!$H$2:$H$766<>""),'Weekly Tracker'!$H$2:$H$766),"") | I215: =IF(H215<>"",LOOKUP(2,1/('Weekly Tracker'!$E$2:$E$766=$A215)/('Weekly Tracker'!$H$2:$H$766<>""),'Weekly Tracker'!$I$2:$I$766),"") | J215: =IFERROR(LOOKUP(2,1/('Weekly Tracker'!$E$2:$E$766=$A215)/('Weekly Tracker'!$J$2:$J$766<>""),'Weekly Tracker'!$J$2:$J$766),"") | K215: =IFERROR(LOOKUP(2,1/('Weekly Tracker'!$E$2:$E$766=$A215)/('Weekly Tracker'!$N$2:$N$766<>""),'Weekly Tracker'!$N$2:$N$766),"") | L215: =IFERROR(LOOKUP(2,1/('Weekly Tracker'!$E$2:$E$766=$A215)/('Weekly Tracker'!$O$2:$O$766<>""),'Weekly Tracker'!$O$2:$O$766),"")
A216: Archie | B216: +91 96324 65650 | F216: =IFERROR(LOOKUP(2,1/('Weekly Tracker'!$E$2:$E$766=$A216)/('Weekly Tracker'!$F$2:$F$766<>""),'Weekly Tracker'!$F$2:$F$766),"") | G216: =IF(F216<>"",LOOKUP(2,1/('Weekly Tracker'!$E$2:$E$766=$A216)/('Weekly Tracker'!$F$2:$F$766<>""),'Weekly Tracker'!$G$2:$G$766),"") | H216: =IFERROR(LOOKUP(2,1/('Weekly Tracker'!$E$2:$E$766=$A216)/('Weekly Tracker'!$H$2:$H$766<>""),'Weekly Tracker'!$H$2:$H$766),"") | I216: =IF(H216<>"",LOOKUP(2,1/('Weekly Tracker'!$E$2:$E$766=$A216)/('Weekly Tracker'!$H$2:$H$766<>""),'Weekly Tracker'!$I$2:$I$766),"") | J216: =IFERROR(LOOKUP(2,1/('Weekly Tracker'!$E$2:$E$766=$A216)/('Weekly Tracker'!$J$2:$J$766<>""),'Weekly Tracker'!$J$2:$J$766),"") | K216: =IFERROR(LOOKUP(2,1/('Weekly Tracker'!$E$2:$E$766=$A216)/('Weekly Tracker'!$N$2:$N$766<>""),'Weekly Tracker'!$N$2:$N$766),"") | L216: =IFERROR(LOOKUP(2,1/('Weekly Tracker'!$E$2:$E$766=$A216)/('Weekly Tracker'!$O$2:$O$766<>""),'Weekly Tracker'!$O$2:$O$766),"")
A217: Pothi Murugan Scl | B217: 919095951133 | F217: =IFERROR(LOOKUP(2,1/('Weekly Tracker'!$E$2:$E$766=$A217)/('Weekly Tracker'!$F$2:$F$766<>""),'Weekly Tracker'!$F$2:$F$766),"") | G217: =IF(F217<>"",LOOKUP(2,1/('Weekly Tracker'!$E$2:$E$766=$A217)/('Weekly Tracker'!$F$2:$F$766<>""),'Weekly Tracker'!$G$2:$G$766),"") | H217: =IFERROR(LOOKUP(2,1/('Weekly Tracker'!$E$2:$E$766=$A217)/('Weekly Tracker'!$H$2:$H$766<>""),'Weekly Tracker'!$H$2:$H$766),"") | I217: =IF(H217<>"",LOOKUP(2,1/('Weekly Tracker'!$E$2:$E$766=$A217)/('Weekly Tracker'!$H$2:$H$766<>""),'Weekly Tracker'!$I$2:$I$766),"") | J217: =IFERROR(LOOKUP(2,1/('Weekly Tracker'!$E$2:$E$766=$A217)/('Weekly Tracker'!$J$2:$J$766<>""),'Weekly Tracker'!$J$2:$J$766),"") | K217: =IFERROR(LOOKUP(2,1/('Weekly Tracker'!$E$2:$E$766=$A217)/('Weekly Tracker'!$N$2:$N$766<>""),'Weekly Tracker'!$N$2:$N$766),"") | L217: =IFERROR(LOOKUP(2,1/('Weekly Tracker'!$E$2:$E$766=$A217)/('Weekly Tracker'!$O$2:$O$766<>""),'Weekly Tracker'!$O$2:$O$766),"")
A218: Karthikeya HCL | B218: 9036281201 | F218: =IFERROR(LOOKUP(2,1/('Weekly Tracker'!$E$2:$E$766=$A218)/('Weekly Tracker'!$F$2:$F$766<>""),'Weekly Tracker'!$F$2:$F$766),"") | G218: =IF(F218<>"",LOOKUP(2,1/('Weekly Tracker'!$E$2:$E$766=$A218)/('Weekly Tracker'!$F$2:$F$766<>""),'Weekly Tracker'!$G$2:$G$766),"") | H218: =IFERROR(LOOKUP(2,1/('Weekly Tracker'!$E$2:$E$766=$A218)/('Weekly Tracker'!$H$2:$H$766<>""),'Weekly Tracker'!$H$2:$H$766),"") | I218: =IF(H218<>"",LOOKUP(2,1/('Weekly Tracker'!$E$2:$E$766=$A218)/('Weekly Tracker'!$H$2:$H$766<>""),'Weekly Tracker'!$I$2:$I$766),"") | J218: =IFERROR(LOOKUP(2,1/('Weekly Tracker'!$E$2:$E$766=$A218)/('Weekly Tracker'!$J$2:$J$766<>""),'Weekly Tracker'!$J$2:$J$766),"") | K218: =IFERROR(LOOKUP(2,1/('Weekly Tracker'!$E$2:$E$766=$A218)/('Weekly Tracker'!$N$2:$N$766<>""),'Weekly Tracker'!$N$2:$N$766),"") | L218: =IFERROR(LOOKUP(2,1/('Weekly Tracker'!$E$2:$E$766=$A218)/('Weekly Tracker'!$O$2:$O$766<>""),'Weekly Tracker'!$O$2:$O$766),"")
A219: Apoorva Gautam HCL | B219: 7987372370 | F219: =IFERROR(LOOKUP(2,1/('Weekly Tracker'!$E$2:$E$766=$A219)/('Weekly Tracker'!$F$2:$F$766<>""),'Weekly Tracker'!$F$2:$F$766),"") | G219: =IF(F219<>"",LOOKUP(2,1/('Weekly Tracker'!$E$2:$E$766=$A219)/('Weekly Tracker'!$F$2:$F$766<>""),'Weekly Tracker'!$G$2:$G$766),"") | H219: =IFERROR(LOOKUP(2,1/('Weekly Tracker'!$E$2:$E$766=$A219)/('Weekly Tracker'!$H$2:$H$766<>""),'Weekly Tracker'!$H$2:$H$766),"") | I219: =IF(H219<>"",LOOKUP(2,1/('Weekly Tracker'!$E$2:$E$766=$A219)/('Weekly Tracker'!$H$2:$H$766<>""),'Weekly Tracker'!$I$2:$I$766),"") | J219: =IFERROR(LOOKUP(2,1/('Weekly Tracker'!$E$2:$E$766=$A219)/('Weekly Tracker'!$J$2:$J$766<>""),'Weekly Tracker'!$J$2:$J$766),"") | K219: =IFERROR(LOOKUP(2,1/('Weekly Tracker'!$E$2:$E$766=$A219)/('Weekly Tracker'!$N$2:$N$766<>""),'Weekly Tracker'!$N$2:$N$766),"") | L219: =IFERROR(LOOKUP(2,1/('Weekly Tracker'!$E$2:$E$766=$A219)/('Weekly Tracker'!$O$2:$O$766<>""),'Weekly Tracker'!$O$2:$O$766),"")
A220: Kali Raj Kprm Scl | B220: 919791639126 | F220: =IFERROR(LOOKUP(2,1/('Weekly Tracker'!$E$2:$E$766=$A220)/('Weekly Tracker'!$F$2:$F$766<>""),'Weekly Tracker'!$F$2:$F$766),"") | G220: =IF(F220<>"",LOOKUP(2,1/('Weekly Tracker'!$E$2:$E$766=$A220)/('Weekly Tracker'!$F$2:$F$766<>""),'Weekly Tracker'!$G$2:$G$766),"") | H220: =IFERROR(LOOKUP(2,1/('Weekly Tracker'!$E$2:$E$766=$A220)/('Weekly Tracker'!$H$2:$H$766<>""),'Weekly Tracker'!$H$2:$H$766),"") | I220: =IF(H220<>"",LOOKUP(2,1/('Weekly Tracker'!$E$2:$E$766=$A220)/('Weekly Tracker'!$H$2:$H$766<>""),'Weekly Tracker'!$I$2:$I$766),"") | J220: =IFERROR(LOOKUP(2,1/('Weekly Tracker'!$E$2:$E$766=$A220)/('Weekly Tracker'!$J$2:$J$766<>""),'Weekly Tracker'!$J$2:$J$766),"") | K220: =IFERROR(LOOKUP(2,1/('Weekly Tracker'!$E$2:$E$766=$A220)/('Weekly Tracker'!$N$2:$N$766<>""),'Weekly Tracker'!$N$2:$N$766),"") | L220: =IFERROR(LOOKUP(2,1/('Weekly Tracker'!$E$2:$E$766=$A220)/('Weekly Tracker'!$O$2:$O$766<>""),'Weekly Tracker'!$O$2:$O$766),"")
A221: ராசா | B221: 918489218328 | F221: =IFERROR(LOOKUP(2,1/('Weekly Tracker'!$E$2:$E$766=$A221)/('Weekly Tracker'!$F$2:$F$766<>""),'Weekly Tracker'!$F$2:$F$766),"") | G221: =IF(F221<>"",LOOKUP(2,1/('Weekly Tracker'!$E$2:$E$766=$A221)/('Weekly Tracker'!$F$2:$F$766<>""),'Weekly Tracker'!$G$2:$G$766),"") | H221: =IFERROR(LOOKUP(2,1/('Weekly Tracker'!$E$2:$E$766=$A221)/('Weekly Tracker'!$H$2:$H$766<>""),'Weekly Tracker'!$H$2:$H$766),"") | I221: =IF(H221<>"",LOOKUP(2,1/('Weekly Tracker'!$E$2:$E$766=$A221)/('Weekly Tracker'!$H$2:$H$766<>""),'Weekly Tracker'!$I$2:$I$766),"") | J221: =IFERROR(LOOKUP(2,1/('Weekly Tracker'!$E$2:$E$766=$A221)/('Weekly Tracker'!$J$2:$J$766<>""),'Weekly Tracker'!$J$2:$J$766),"") | K221: =IFERROR(LOOKUP(2,1/('Weekly Tracker'!$E$2:$E$766=$A221)/('Weekly Tracker'!$N$2:$N$766<>""),'Weekly Tracker'!$N$2:$N$766),"") | L221: =IFERROR(LOOKUP(2,1/('Weekly Tracker'!$E$2:$E$766=$A221)/('Weekly Tracker'!$O$2:$O$766<>""),'Weekly Tracker'!$O$2:$O$766),"")
A222: Selvin FB | B222: 9944274617 | F222: =IFERROR(LOOKUP(2,1/('Weekly Tracker'!$E$2:$E$766=$A222)/('Weekly Tracker'!$F$2:$F$766<>""),'Weekly Tracker'!$F$2:$F$766),"") | G222: =IF(F222<>"",LOOKUP(2,1/('Weekly Tracker'!$E$2:$E$766=$A222)/('Weekly Tracker'!$F$2:$F$766<>""),'Weekly Tracker'!$G$2:$G$766),"") | H222: =IFERROR(LOOKUP(2,1/('Weekly Tracker'!$E$2:$E$766=$A222)/('Weekly Tracker'!$H$2:$H$766<>""),'Weekly Tracker'!$H$2:$H$766),"") | I222: =IF(H222<>"",LOOKUP(2,1/('Weekly Tracker'!$E$2:$E$766=$A222)/('Weekly Tracker'!$H$2:$H$766<>""),'Weekly Tracker'!$I$2:$I$766),"") | J222: =IFERROR(LOOKUP(2,1/('Weekly Tracker'!$E$2:$E$766=$A222)/('Weekly Tracker'!$J$2:$J$766<>""),'Weekly Tracker'!$J$2:$J$766),"") | K222: =IFERROR(LOOKUP(2,1/('Weekly Tracker'!$E$2:$E$766=$A222)/('Weekly Tracker'!$N$2:$N$766<>""),'Weekly Tracker'!$N$2:$N$766),"") | L222: =IFERROR(LOOKUP(2,1/('Weekly Tracker'!$E$2:$E$766=$A222)/('Weekly Tracker'!$O$2:$O$766<>""),'Weekly Tracker'!$O$2:$O$766),"")
A223: Jeflin Grp Ucen | B223: 919597180286, 9445180980 | F223: =IFERROR(LOOKUP(2,1/('Weekly Tracker'!$E$2:$E$766=$A223)/('Weekly Tracker'!$F$2:$F$766<>""),'Weekly Tracker'!$F$2:$F$766),"") | G223: =IF(F223<>"",LOOKUP(2,1/('Weekly Tracker'!$E$2:$E$766=$A223)/('Weekly Tracker'!$F$2:$F$766<>""),'Weekly Tracker'!$G$2:$G$766),"") | H223: =IFERROR(LOOKUP(2,1/('Weekly Tracker'!$E$2:$E$766=$A223)/('Weekly Tracker'!$H$2:$H$766<>""),'Weekly Tracker'!$H$2:$H$766),"") | I223: =IF(H223<>"",LOOKUP(2,1/('Weekly Tracker'!$E$2:$E$766=$A223)/('Weekly Tracker'!$H$2:$H$766<>""),'Weekly Tracker'!$I$2:$I$766),"") | J223: =IFERROR(LOOKUP(2,1/('Weekly Tracker'!$E$2:$E$766=$A223)/('Weekly Tracker'!$J$2:$J$766<>""),'Weekly Tracker'!$J$2:$J$766),"") | K223: =IFERROR(LOOKUP(2,1/('Weekly Tracker'!$E$2:$E$766=$A223)/('Weekly Tracker'!$N$2:$N$766<>""),'Weekly Tracker'!$N$2:$N$766),"") | L223: =IFERROR(LOOKUP(2,1/('Weekly Tracker'!$E$2:$E$766=$A223)/('Weekly Tracker'!$O$2:$O$766<>""),'Weekly Tracker'!$O$2:$O$766),"")
A224: Pravin qs | B224: 919840942211 | F224: =IFERROR(LOOKUP(2,1/('Weekly Tracker'!$E$2:$E$766=$A224)/('Weekly Tracker'!$F$2:$F$766<>""),'Weekly Tracker'!$F$2:$F$766),"") | G224: =IF(F224<>"",LOOKUP(2,1/('Weekly Tracker'!$E$2:$E$766=$A224)/('Weekly Tracker'!$F$2:$F$766<>""),'Weekly Tracker'!$G$2:$G$766),"") | H224: =IFERROR(LOOKUP(2,1/('Weekly Tracker'!$E$2:$E$766=$A224)/('Weekly Tracker'!$H$2:$H$766<>""),'Weekly Tracker'!$H$2:$H$766),"") | I224: =IF(H224<>"",LOOKUP(2,1/('Weekly Tracker'!$E$2:$E$766=$A224)/('Weekly Tracker'!$H$2:$H$766<>""),'Weekly Tracker'!$I$2:$I$766),"") | J224: =IFERROR(LOOKUP(2,1/('Weekly Tracker'!$E$2:$E$766=$A224)/('Weekly Tracker'!$J$2:$J$766<>""),'Weekly Tracker'!$J$2:$J$766),"") | K224: =IFERROR(LOOKUP(2,1/('Weekly Tracker'!$E$2:$E$766=$A224)/('Weekly Tracker'!$N$2:$N$766<>""),'Weekly Tracker'!$N$2:$N$766),"") | L224: =IFERROR(LOOKUP(2,1/('Weekly Tracker'!$E$2:$E$766=$A224)/('Weekly Tracker'!$O$2:$O$766<>""),'Weekly Tracker'!$O$2:$O$766),"")
A225: SamKumar HCL | B225: 9176737071 | F225: =IFERROR(LOOKUP(2,1/('Weekly Tracker'!$E$2:$E$766=$A225)/('Weekly Tracker'!$F$2:$F$766<>""),'Weekly Tracker'!$F$2:$F$766),"") | G225: =IF(F225<>"",LOOKUP(2,1/('Weekly Tracker'!$E$2:$E$766=$A225)/('Weekly Tracker'!$F$2:$F$766<>""),'Weekly Tracker'!$G$2:$G$766),"") | H225: =IFERROR(LOOKUP(2,1/('Weekly Tracker'!$E$2:$E$766=$A225)/('Weekly Tracker'!$H$2:$H$766<>""),'Weekly Tracker'!$H$2:$H$766),"") | I225: =IF(H225<>"",LOOKUP(2,1/('Weekly Tracker'!$E$2:$E$766=$A225)/('Weekly Tracker'!$H$2:$H$766<>""),'Weekly Tracker'!$I$2:$I$766),"") | J225: =IFERROR(LOOKUP(2,1/('Weekly Tracker'!$E$2:$E$766=$A225)/('Weekly Tracker'!$J$2:$J$766<>""),'Weekly Tracker'!$J$2:$J$766),"") | K225: =IFERROR(LOOKUP(2,1/('Weekly Tracker'!$E$2:$E$766=$A225)/('Weekly Tracker'!$N$2:$N$766<>""),'Weekly Tracker'!$N$2:$N$766),"") | L225: =IFERROR(LOOKUP(2,1/('Weekly Tracker'!$E$2:$E$766=$A225)/('Weekly Tracker'!$O$2:$O$766<>""),'Weekly Tracker'!$O$2:$O$766),"")
A226: HarishAkhepuriya Painting Infy | B226: 919716299792 | F226: =IFERROR(LOOKUP(2,1/('Weekly Tracker'!$E$2:$E$766=$A226)/('Weekly Tracker'!$F$2:$F$766<>""),'Weekly Tracker'!$F$2:$F$766),"") | G226: =IF(F226<>"",LOOKUP(2,1/('Weekly Tracker'!$E$2:$E$766=$A226)/('Weekly Tracker'!$F$2:$F$766<>""),'Weekly Tracker'!$G$2:$G$766),"") | H226: =IFERROR(LOOKUP(2,1/('Weekly Tracker'!$E$2:$E$766=$A226)/('Weekly Tracker'!$H$2:$H$766<>""),'Weekly Tracker'!$H$2:$H$766),"") | I226: =IF(H226<>"",LOOKUP(2,1/('Weekly Tracker'!$E$2:$E$766=$A226)/('Weekly Tracker'!$H$2:$H$766<>""),'Weekly Tracker'!$I$2:$I$766),"") | J226: =IFERROR(LOOKUP(2,1/('Weekly Tracker'!$E$2:$E$766=$A226)/('Weekly Tracker'!$J$2:$J$766<>""),'Weekly Tracker'!$J$2:$J$766),"") | K226: =IFERROR(LOOKUP(2,1/('Weekly Tracker'!$E$2:$E$766=$A226)/('Weekly Tracker'!$N$2:$N$766<>""),'Weekly Tracker'!$N$2:$N$766),"") | L226: =IFERROR(LOOKUP(2,1/('Weekly Tracker'!$E$2:$E$766=$A226)/('Weekly Tracker'!$O$2:$O$766<>""),'Weekly Tracker'!$O$2:$O$766),"")
... A324: Veera Telegram | B324: 9014515419 | F324: =IFERROR(LOOKUP(2,1/('Weekly Tracker'!$E$2:$E$766=$A324)/('Weekly Tracker'!$F$2:$F$766<>""),'Weekly Tracker'!$F$2:$F$766),"") | G324: =IF(F324<>"",LOOKUP(2,1/('Weekly Tracker'!$E$2:$E$766=$A324)/('Weekly Tracker'!$F$2:$F$766<>""),'Weekly Tracker'!$G$2:$G$766),"") | H324: =IFERROR(LOOKUP(2,1/('Weekly Tracker'!$E$2:$E$766=$A324)/('Weekly Tracker'!$H$2:$H$766<>""),'Weekly Tracker'!$H$2:$H$766),"") | I324: =IF(H324<>"",LOOKUP(2,1/('Weekly Tracker'!$E$2:$E$766=$A324)/('Weekly Tracker'!$H$2:$H$766<>""),'Weekly Tracker'!$I$2:$I$766),"") | J324: =IFERROR(LOOKUP(2,1/('Weekly Tracker'!$E$2:$E$766=$A324)/('Weekly Tracker'!$J$2:$J$766<>""),'Weekly Tracker'!$J$2:$J$766),"") | K324: =IFERROR(LOOKUP(2,1/('Weekly Tracker'!$E$2:$E$766=$A324)/('Weekly Tracker'!$N$2:$N$766<>""),'Weekly Tracker'!$N$2:$N$766),"") | L324: =IFERROR(LOOKUP(2,1/('Weekly Tracker'!$E$2:$E$766=$A324)/('Weekly Tracker'!$O$2:$O$766<>""),'Weekly Tracker'!$O$2:$O$766),"")
A325: Shenbaga Velu Scl | B325: 917806921030 | E325: Tamil Nadu, India | F325: =IFERROR(LOOKUP(2,1/('Weekly Tracker'!$E$2:$E$766=$A325)/('Weekly Tracker'!$F$2:$F$766<>""),'Weekly Tracker'!$F$2:$F$766),"") | G325: =IF(F325<>"",LOOKUP(2,1/('Weekly Tracker'!$E$2:$E$766=$A325)/('Weekly Tracker'!$F$2:$F$766<>""),'Weekly Tracker'!$G$2:$G$766),"") | H325: =IFERROR(LOOKUP(2,1/('Weekly Tracker'!$E$2:$E$766=$A325)/('Weekly Tracker'!$H$2:$H$766<>""),'Weekly Tracker'!$H$2:$H$766),"") | I325: =IF(H325<>"",LOOKUP(2,1/('Weekly Tracker'!$E$2:$E$766=$A325)/('Weekly Tracker'!$H$2:$H$766<>""),'Weekly Tracker'!$I$2:$I$766),"") | J325: =IFERROR(LOOKUP(2,1/('Weekly Tracker'!$E$2:$E$766=$A325)/('Weekly Tracker'!$J$2:$J$766<>""),'Weekly Tracker'!$J$2:$J$766),"") | K325: =IFERROR(LOOKUP(2,1/('Weekly Tracker'!$E$2:$E$766=$A325)/('Weekly Tracker'!$N$2:$N$766<>""),'Weekly Tracker'!$N$2:$N$766),"") | L325: =IFERROR(LOOKUP(2,1/('Weekly Tracker'!$E$2:$E$766=$A325)/('Weekly Tracker'!$O$2:$O$766<>""),'Weekly Tracker'!$O$2:$O$766),"")
A326: Claybag | B326: 919742263339 | F326: =IFERROR(LOOKUP(2,1/('Weekly Tracker'!$E$2:$E$766=$A326)/('Weekly Tracker'!$F$2:$F$766<>""),'Weekly Tracker'!$F$2:$F$766),"") | G326: =IF(F326<>"",LOOKUP(2,1/('Weekly Tracker'!$E$2:$E$766=$A326)/('Weekly Tracker'!$F$2:$F$766<>""),'Weekly Tracker'!$G$2:$G$766),"") | H326: =IFERROR(LOOKUP(2,1/('Weekly Tracker'!$E$2:$E$766=$A326)/('Weekly Tracker'!$H$2:$H$766<>""),'Weekly Tracker'!$H$2:$H$766),"") | I326: =IF(H326<>"",LOOKUP(2,1/('Weekly Tracker'!$E$2:$E$766=$A326)/('Weekly Tracker'!$H$2:$H$766<>""),'Weekly Tracker'!$I$2:$I$766),"") | J326: =IFERROR(LOOKUP(2,1/('Weekly Tracker'!$E$2:$E$766=$A326)/('Weekly Tracker'!$J$2:$J$766<>""),'Weekly Tracker'!$J$2:$J$766),"") | K326: =IFERROR(LOOKUP(2,1/('Weekly Tracker'!$E$2:$E$766=$A326)/('Weekly Tracker'!$N$2:$N$766<>""),'Weekly Tracker'!$N$2:$N$766),"") | L326: =IFERROR(LOOKUP(2,1/('Weekly Tracker'!$E$2:$E$766=$A326)/('Weekly Tracker'!$O$2:$O$766<>""),'Weekly Tracker'!$O$2:$O$766),"")
A327: Vimal Loan Loan Axis | B327: 917904628887 | F327: =IFERROR(LOOKUP(2,1/('Weekly Tracker'!$E$2:$E$766=$A327)/('Weekly Tracker'!$F$2:$F$766<>""),'Weekly Tracker'!$F$2:$F$766),"") | G327: =IF(F327<>"",LOOKUP(2,1/('Weekly Tracker'!$E$2:$E$766=$A327)/('Weekly Tracker'!$F$2:$F$766<>""),'Weekly Tracker'!$G$2:$G$766),"") | H327: =IFERROR(LOOKUP(2,1/('Weekly Tracker'!$E$2:$E$766=$A327)/('Weekly Tracker'!$H$2:$H$766<>""),'Weekly Tracker'!$H$2:$H$766),"") | I327: =IF(H327<>"",LOOKUP(2,1/('Weekly Tracker'!$E$2:$E$766=$A327)/('Weekly Tracker'!$H$2:$H$766<>""),'Weekly Tracker'!$I$2:$I$766),"") | J327: =IFERROR(LOOKUP(2,1/('Weekly Tracker'!$E$2:$E$766=$A327)/('Weekly Tracker'!$J$2:$J$766<>""),'Weekly Tracker'!$J$2:$J$766),"") | K327: =IFERROR(LOOKUP(2,1/('Weekly Tracker'!$E$2:$E$766=$A327)/('Weekly Tracker'!$N$2:$N$766<>""),'Weekly Tracker'!$N$2:$N$766),"") | L327: =IFERROR(LOOKUP(2,1/('Weekly Tracker'!$E$2:$E$766=$A327)/('Weekly Tracker'!$O$2:$O$766<>""),'Weekly Tracker'!$O$2:$O$766),"")
A328: Rock Agastin FB | B328: 8675602251 | F328: =IFERROR(LOOKUP(2,1/('Weekly Tracker'!$E$2:$E$766=$A328)/('Weekly Tracker'!$F$2:$F$766<>""),'Weekly Tracker'!$F$2:$F$766),"") | G328: =IF(F328<>"",LOOKUP(2,1/('Weekly Tracker'!$E$2:$E$766=$A328)/('Weekly Tracker'!$F$2:$F$766<>""),'Weekly Tracker'!$G$2:$G$766),"") | H328: =IFERROR(LOOKUP(2,1/('Weekly Tracker'!$E$2:$E$766=$A328)/('Weekly Tracker'!$H$2:$H$766<>""),'Weekly Tracker'!$H$2:$H$766),"") | I328: =IF(H328<>"",LOOKUP(2,1/('Weekly Tracker'!$E$2:$E$766=$A328)/('Weekly Tracker'!$H$2:$H$766<>""),'Weekly Tracker'!$I$2:$I$766),"") | J328: =IFERROR(LOOKUP(2,1/('Weekly Tracker'!$E$2:$E$766=$A328)/('Weekly Tracker'!$J$2:$J$766<>""),'Weekly Tracker'!$J$2:$J$766),"") | K328: =IFERROR(LOOKUP(2,1/('Weekly Tracker'!$E$2:$E$766=$A328)/('Weekly Tracker'!$N$2:$N$766<>""),'Weekly Tracker'!$N$2:$N$766),"") | L328: =IFERROR(LOOKUP(2,1/('Weekly Tracker'!$E$2:$E$766=$A328)/('Weekly Tracker'!$O$2:$O$766<>""),'Weekly Tracker'!$O$2:$O$766),"")
A329: Dhinesh Dsp FB | B329: 7639554324 | F329: =IFERROR(LOOKUP(2,1/('Weekly Tracker'!$E$2:$E$766=$A329)/('Weekly Tracker'!$F$2:$F$766<>""),'Weekly Tracker'!$F$2:$F$766),"") | G329: =IF(F329<>"",LOOKUP(2,1/('Weekly Tracker'!$E$2:$E$766=$A329)/('Weekly Tracker'!$F$2:$F$766<>""),'Weekly Tracker'!$G$2:$G$766),"") | H329: =IFERROR(LOOKUP(2,1/('Weekly Tracker'!$E$2:$E$766=$A329)/('Weekly Tracker'!$H$2:$H$766<>""),'Weekly Tracker'!$H$2:$H$766),"") | I329: =IF(H329<>"",LOOKUP(2,1/('Weekly Tracker'!$E$2:$E$766=$A329)/('Weekly Tracker'!$H$2:$H$766<>""),'Weekly Tracker'!$I$2:$I$766),"") | J329: =IFERROR(LOOKUP(2,1/('Weekly Tracker'!$E$2:$E$766=$A329)/('Weekly Tracker'!$J$2:$J$766<>""),'Weekly Tracker'!$J$2:$J$766),"") | K329: =IFERROR(LOOKUP(2,1/('Weekly Tracker'!$E$2:$E$766=$A329)/('Weekly Tracker'!$N$2:$N$766<>""),'Weekly Tracker'!$N$2:$N$766),"") | L329: =IFERROR(LOOKUP(2,1/('Weekly Tracker'!$E$2:$E$766=$A329)/('Weekly Tracker'!$O$2:$O$766<>""),'Weekly Tracker'!$O$2:$O$766),"")
A330: Deepak Charter Infy | B330: 918667319991 | F330: =IFERROR(LOOKUP(2,1/('Weekly Tracker'!$E$2:$E$766=$A330)/('Weekly Tracker'!$F$2:$F$766<>""),'Weekly Tracker'!$F$2:$F$766),"") | G330: =IF(F330<>"",LOOKUP(2,1/('Weekly Tracker'!$E$2:$E$766=$A330)/('Weekly Tracker'!$F$2:$F$766<>""),'Weekly Tracker'!$G$2:$G$766),"") | H330: =IFERROR(LOOKUP(2,1/('Weekly Tracker'!$E$2:$E$766=$A330)/('Weekly Tracker'!$H$2:$H$766<>""),'Weekly Tracker'!$H$2:$H$766),"") | I330: =IF(H330<>"",LOOKUP(2,1/('Weekly Tracker'!$E$2:$E$766=$A330)/('Weekly Tracker'!$H$2:$H$766<>""),'Weekly Tracker'!$I$2:$I$766),"") | J330: =IFERROR(LOOKUP(2,1/('Weekly Tracker'!$E$2:$E$766=$A330)/('Weekly Tracker'!$J$2:$J$766<>""),'Weekly Tracker'!$J$2:$J$766),"") | K330: =IFERROR(LOOKUP(2,1/('Weekly Tracker'!$E$2:$E$766=$A330)/('Weekly Tracker'!$N$2:$N$766<>""),'Weekly Tracker'!$N$2:$N$766),"") | L330: =IFERROR(LOOKUP(2,1/('Weekly Tracker'!$E$2:$E$766=$A330)/('Weekly Tracker'!$O$2:$O$766<>""),'Weekly Tracker'!$O$2:$O$766),"")
A331: Joy HDFC | B331: 919043562823 | F331: =IFERROR(LOOKUP(2,1/('Weekly Tracker'!$E$2:$E$766=$A331)/('Weekly Tracker'!$F$2:$F$766<>""),'Weekly Tracker'!$F$2:$F$766),"") | G331: =IF(F331<>"",LOOKUP(2,1/('Weekly Tracker'!$E$2:$E$766=$A331)/('Weekly Tracker'!$F$2:$F$766<>""),'Weekly Tracker'!$G$2:$G$766),"") | H331: =IFERROR(LOOKUP(2,1/('Weekly Tracker'!$E$2:$E$766=$A331)/('Weekly Tracker'!$H$2:$H$766<>""),'Weekly Tracker'!$H$2:$H$766),"") | I331: =IF(H331<>"",LOOKUP(2,1/('Weekly Tracker'!$E$2:$E$766=$A331)/('Weekly Tracker'!$H$2:$H$766<>""),'Weekly Tracker'!$I$2:$I$766),"") | J331: =IFERROR(LOOKUP(2,1/('Weekly Tracker'!$E$2:$E$766=$A331)/('Weekly Tracker'!$J$2:$J$766<>""),'Weekly Tracker'!$J$2:$J$766),"") | K331: =IFERROR(LOOKUP(2,1/('Weekly Tracker'!$E$2:$E$766=$A331)/('Weekly Tracker'!$N$2:$N$766<>""),'Weekly Tracker'!$N$2:$N$766),"") | L331: =IFERROR(LOOKUP(2,1/('Weekly Tracker'!$E$2:$E$766=$A331)/('Weekly Tracker'!$O$2:$O$766<>""),'Weekly Tracker'!$O$2:$O$766),"")
A332: Ponraj | B332: 9597375734 | E332: Tamil Nadu, India | F332: =IFERROR(LOOKUP(2,1/('Weekly Tracker'!$E$2:$E$766=$A332)/('Weekly Tracker'!$F$2:$F$766<>""),'Weekly Tracker'!$F$2:$F$766),"") | G332: =IF(F332<>"",LOOKUP(2,1/('Weekly Tracker'!$E$2:$E$766=$A332)/('Weekly Tracker'!$F$2:$F$766<>""),'Weekly Tracker'!$G$2:$G$766),"") | H332: =IFERROR(LOOKUP(2,1/('Weekly Tracker'!$E$2:$E$766=$A332)/('Weekly Tracker'!$H$2:$H$766<>""),'Weekly Tracker'!$H$2:$H$766),"") | I332: =IF(H332<>"",LOOKUP(2,1/('Weekly Tracker'!$E$2:$E$766=$A332)/('Weekly Tracker'!$H$2:$H$766<>""),'Weekly Tracker'!$I$2:$I$766),"") | J332: =IFERROR(LOOKUP(2,1/('Weekly Tracker'!$E$2:$E$766=$A332)/('Weekly Tracker'!$J$2:$J$766<>""),'Weekly Tracker'!$J$2:$J$766),"") | K332: =IFERROR(LOOKUP(2,1/('Weekly Tracker'!$E$2:$E$766=$A332)/('Weekly Tracker'!$N$2:$N$766<>""),'Weekly Tracker'!$N$2:$N$766),"") | L332: =IFERROR(LOOKUP(2,1/('Weekly Tracker'!$E$2:$E$766=$A332)/('Weekly Tracker'!$O$2:$O$766<>""),'Weekly Tracker'!$O$2:$O$766),"")
A333: Vignesh Monitoring Urja | B333: 919791364365 | F333: =IFERROR(LOOKUP(2,1/('Weekly Tracker'!$E$2:$E$766=$A333)/('Weekly Tracker'!$F$2:$F$766<>""),'Weekly Tracker'!$F$2:$F$766),"") | G333: =IF(F333<>"",LOOKUP(2,1/('Weekly Tracker'!$E$2:$E$766=$A333)/('Weekly Tracker'!$F$2:$F$766<>""),'Weekly Tracker'!$G$2:$G$766),"") | H333: =IFERROR(LOOKUP(2,1/('Weekly Tracker'!$E$2:$E$766=$A333)/('Weekly Tracker'!$H$2:$H$766<>""),'Weekly Tracker'!$H$2:$H$766),"") | I333: =IF(H333<>"",LOOKUP(2,1/('Weekly Tracker'!$E$2:$E$766=$A333)/('Weekly Tracker'!$H$2:$H$766<>""),'Weekly Tracker'!$I$2:$I$766),"") | J333: =IFERROR(LOOKUP(2,1/('Weekly Tracker'!$E$2:$E$766=$A333)/('Weekly Tracker'!$J$2:$J$766<>""),'Weekly Tracker'!$J$2:$J$766),"") | K333: =IFERROR(LOOKUP(2,1/('Weekly Tracker'!$E$2:$E$766=$A333)/('Weekly Tracker'!$N$2:$N$766<>""),'Weekly Tracker'!$N$2:$N$766),"") | L333: =IFERROR(LOOKUP(2,1/('Weekly Tracker'!$E$2:$E$766=$A333)/('Weekly Tracker'!$O$2:$O$766<>""),'Weekly Tracker'!$O$2:$O$766),"")
A334: Jason Dharmaraj FB | B334: 918348945649 | F334: =IFERROR(LOOKUP(2,1/('Weekly Tracker'!$E$2:$E$766=$A334)/('Weekly Tracker'!$F$2:$F$766<>""),'Weekly Tracker'!$F$2:$F$766),"") | G334: =IF(F334<>"",LOOKUP(2,1/('Weekly Tracker'!$E$2:$E$766=$A334)/('Weekly Tracker'!$F$2:$F$766<>""),'Weekly Tracker'!$G$2:$G$766),"") | H334: =IFERROR(LOOKUP(2,1/('Weekly Tracker'!$E$2:$E$766=$A334)/('Weekly Tracker'!$H$2:$H$766<>""),'Weekly Tracker'!$H$2:$H$766),"") | I334: =IF(H334<>"",LOOKUP(2,1/('Weekly Tracker'!$E$2:$E$766=$A334)/('Weekly Tracker'!$H$2:$H$766<>""),'Weekly Tracker'!$I$2:$I$766),"") | J334: =IFERROR(LOOKUP(2,1/('Weekly Tracker'!$E$2:$E$766=$A334)/('Weekly Tracker'!$J$2:$J$766<>""),'Weekly Tracker'!$J$2:$J$766),"") | K334: =IFERROR(LOOKUP(2,1/('Weekly Tracker'!$E$2:$E$766=$A334)/('Weekly Tracker'!$N$2:$N$766<>""),'Weekly Tracker'!$N$2:$N$766),"") | L334: =IFERROR(LOOKUP(2,1/('Weekly Tracker'!$E$2:$E$766=$A334)/('Weekly Tracker'!$O$2:$O$766<>""),'Weekly Tracker'!$O$2:$O$766),"")
A335: Pandi Durai FB | B335: 918883242806 | F335: =IFERROR(LOOKUP(2,1/('Weekly Tracker'!$E$2:$E$766=$A335)/('Weekly Tracker'!$F$2:$F$766<>""),'Weekly Tracker'!$F$2:$F$766),"") | G335: =IF(F335<>"",LOOKUP(2,1/('Weekly Tracker'!$E$2:$E$766=$A335)/('Weekly Tracker'!$F$2:$F$766<>""),'Weekly Tracker'!$G$2:$G$766),"") | H335: =IFERROR(LOOKUP(2,1/('Weekly Tracker'!$E$2:$E$766=$A335)/('Weekly Tracker'!$H$2:$H$766<>""),'Weekly Tracker'!$H$2:$H$766),"") | I335: =IF(H335<>"",LOOKUP(2,1/('Weekly Tracker'!$E$2:$E$766=$A335)/('Weekly Tracker'!$H$2:$H$766<>""),'Weekly Tracker'!$I$2:$I$766),"") | J335: =IFERROR(LOOKUP(2,1/('Weekly Tracker'!$E$2:$E$766=$A335)/('Weekly Tracker'!$J$2:$J$766<>""),'Weekly Tracker'!$J$2:$J$766),"") | K335: =IFERROR(LOOKUP(2,1/('Weekly Tracker'!$E$2:$E$766=$A335)/('Weekly Tracker'!$N$2:$N$766<>""),'Weekly Tracker'!$N$2:$N$766),"") | L335: =IFERROR(LOOKUP(2,1/('Weekly Tracker'!$E$2:$E$766=$A335)/('Weekly Tracker'!$O$2:$O$766<>""),'Weekly Tracker'!$O$2:$O$766),"")
A336: Avitam Homes | B336: 919884972241 | F336: =IFERROR(LOOKUP(2,1/('Weekly Tracker'!$E$2:$E$766=$A336)/('Weekly Tracker'!$F$2:$F$766<>""),'Weekly Tracker'!$F$2:$F$766),"") | G336: =IF(F336<>"",LOOKUP(2,1/('Weekly Tracker'!$E$2:$E$766=$A336)/('Weekly Tracker'!$F$2:$F$766<>""),'Weekly Tracker'!$G$2:$G$766),"") | H336: =IFERROR(LOOKUP(2,1/('Weekly Tracker'!$E$2:$E$766=$A336)/('Weekly Tracker'!$H$2:$H$766<>""),'Weekly Tracker'!$H$2:$H$766),"") | I336: =IF(H336<>"",LOOKUP(2,1/('Weekly Tracker'!$E$2:$E$766=$A336)/('Weekly Tracker'!$H$2:$H$766<>""),'Weekly Tracker'!$I$2:$I$766),"") | J336: =IFERROR(LOOKUP(2,1/('Weekly Tracker'!$E$2:$E$766=$A336)/('Weekly Tracker'!$J$2:$J$766<>""),'Weekly Tracker'!$J$2:$J$766),"") | K336: =IFERROR(LOOKUP(2,1/('Weekly Tracker'!$E$2:$E$766=$A336)/('Weekly Tracker'!$N$2:$N$766<>""),'Weekly Tracker'!$N$2:$N$766),"") | L336: =IFERROR(LOOKUP(2,1/('Weekly Tracker'!$E$2:$E$766=$A336)/('Weekly Tracker'!$O$2:$O$766<>""),'Weekly Tracker'!$O$2:$O$766),"")
A337: Ravirajan Ravichandran | B337: 9688485621 | F337: =IFERROR(LOOKUP(2,1/('Weekly Tracker'!$E$2:$E$766=$A337)/('Weekly Tracker'!$F$2:$F$766<>""),'Weekly Tracker'!$F$2:$F$766),"") | G337: =IF(F337<>"",LOOKUP(2,1/('Weekly Tracker'!$E$2:$E$766=$A337)/('Weekly Tracker'!$F$2:$F$766<>""),'Weekly Tracker'!$G$2:$G$766),"") | H337: =IFERROR(LOOKUP(2,1/('Weekly Tracker'!$E$2:$E$766=$A337)/('Weekly Tracker'!$H$2:$H$766<>""),'Weekly Tracker'!$H$2:$H$766),"") | I337: =IF(H337<>"",LOOKUP(2,1/('Weekly Tracker'!$E$2:$E$766=$A337)/('Weekly Tracker'!$H$2:$H$766<>""),'Weekly Tracker'!$I$2:$I$766),"") | J337: =IFERROR(LOOKUP(2,1/('Weekly Tracker'!$E$2:$E$766=$A337)/('Weekly Tracker'!$J$2:$J$766<>""),'Weekly Tracker'!$J$2:$J$766),"") | K337: =IFERROR(LOOKUP(2,1/('Weekly Tracker'!$E$2:$E$766=$A337)/('Weekly Tracker'!$N$2:$N$766<>""),'Weekly Tracker'!$N$2:$N$766),"") | L337: =IFERROR(LOOKUP(2,1/('Weekly Tracker'!$E$2:$E$766=$A337)/('Weekly Tracker'!$O$2:$O$766<>""),'Weekly Tracker'!$O$2:$O$766),"")
A338: Sethu Urja | B338: 919500240048 | F338: =IFERROR(LOOKUP(2,1/('Weekly Tracker'!$E$2:$E$766=$A338)/('Weekly Tracker'!$F$2:$F$766<>""),'Weekly Tracker'!$F$2:$F$766),"") | G338: =IF(F338<>"",LOOKUP(2,1/('Weekly Tracker'!$E$2:$E$766=$A338)/('Weekly Tracker'!$F$2:$F$766<>""),'Weekly Tracker'!$G$2:$G$766),"") | H338: =IFERROR(LOOKUP(2,1/('Weekly Tracker'!$E$2:$E$766=$A338)/('Weekly Tracker'!$H$2:$H$766<>""),'Weekly Tracker'!$H$2:$H$766),"") | I338: =IF(H338<>"",LOOKUP(2,1/('Weekly Tracker'!$E$2:$E$766=$A338)/('Weekly Tracker'!$H$2:$H$766<>""),'Weekly Tracker'!$I$2:$I$766),"") | J338: =IFERROR(LOOKUP(2,1/('Weekly Tracker'!$E$2:$E$766=$A338)/('Weekly Tracker'!$J$2:$J$766<>""),'Weekly Tracker'!$J$2:$J$766),"") | K338: =IFERROR(LOOKUP(2,1/('Weekly Tracker'!$E$2:$E$766=$A338)/('Weekly Tracker'!$N$2:$N$766<>""),'Weekly Tracker'!$N$2:$N$766),"") | L338: =IFERROR(LOOKUP(2,1/('Weekly Tracker'!$E$2:$E$766=$A338)/('Weekly Tracker'!$O$2:$O$766<>""),'Weekly Tracker'!$O$2:$O$766),"")
A339: Prem Mech | B339: 917200775368 | F339: =IFERROR(LOOKUP(2,1/('Weekly Tracker'!$E$2:$E$766=$A339)/('Weekly Tracker'!$F$2:$F$766<>""),'Weekly Tracker'!$F$2:$F$766),"") | G339: =IF(F339<>"",LOOKUP(2,1/('Weekly Tracker'!$E$2:$E$766=$A339)/('Weekly Tracker'!$F$2:$F$766<>""),'Weekly Tracker'!$G$2:$G$766),"") | H339: =IFERROR(LOOKUP(2,1/('Weekly Tracker'!$E$2:$E$766=$A339)/('Weekly Tracker'!$H$2:$H$766<>""),'Weekly Tracker'!$H$2:$H$766),"") | I339: =IF(H339<>"",LOOKUP(2,1/('Weekly Tracker'!$E$2:$E$766=$A339)/('Weekly Tracker'!$H$2:$H$766<>""),'Weekly Tracker'!$I$2:$I$766),"") | J339: =IFERROR(LOOKUP(2,1/('Weekly Tracker'!$E$2:$E$766=$A339)/('Weekly Tracker'!$J$2:$J$766<>""),'Weekly Tracker'!$J$2:$J$766),"") | K339: =IFERROR(LOOKUP(2,1/('Weekly Tracker'!$E$2:$E$766=$A339)/('Weekly Tracker'!$N$2:$N$766<>""),'Weekly Tracker'!$N$2:$N$766),"") | L339: =IFERROR(LOOKUP(2,1/('Weekly Tracker'!$E$2:$E$766=$A339)/('Weekly Tracker'!$O$2:$O$766<>""),'Weekly Tracker'!$O$2:$O$766),"")
A340: Merline Mary Urja | B340: 919087183586 | F340: =IFERROR(LOOKUP(2,1/('Weekly Tracker'!$E$2:$E$766=$A340)/('Weekly Tracker'!$F$2:$F$766<>""),'Weekly Tracker'!$F$2:$F$766),"") | G340: =IF(F340<>"",LOOKUP(2,1/('Weekly Tracker'!$E$2:$E$766=$A340)/('Weekly Tracker'!$F$2:$F$766<>""),'Weekly Tracker'!$G$2:$G$766),"") | H340: =IFERROR(LOOKUP(2,1/('Weekly Tracker'!$E$2:$E$766=$A340)/('Weekly Tracker'!$H$2:$H$766<>""),'Weekly Tracker'!$H$2:$H$766),"") | I340: =IF(H340<>"",LOOKUP(2,1/('Weekly Tracker'!$E$2:$E$766=$A340)/('Weekly Tracker'!$H$2:$H$766<>""),'Weekly Tracker'!$I$2:$I$766),"") | J340: =IFERROR(LOOKUP(2,1/('Weekly Tracker'!$E$2:$E$766=$A340)/('Weekly Tracker'!$J$2:$J$766<>""),'Weekly Tracker'!$J$2:$J$766),"") | K340: =IFERROR(LOOKUP(2,1/('Weekly Tracker'!$E$2:$E$766=$A340)/('Weekly Tracker'!$N$2:$N$766<>""),'Weekly Tracker'!$N$2:$N$766),"") | L340: =IFERROR(LOOKUP(2,1/('Weekly Tracker'!$E$2:$E$766=$A340)/('Weekly Tracker'!$O$2:$O$766<>""),'Weekly Tracker'!$O$2:$O$766),"")
A341: Uma Shankar Infy UCC | B341: 919944829200 | F341: =IFERROR(LOOKUP(2,1/('Weekly Tracker'!$E$2:$E$766=$A341)/('Weekly Tracker'!$F$2:$F$766<>""),'Weekly Tracker'!$F$2:$F$766),"") | G341: =IF(F341<>"",LOOKUP(2,1/('Weekly Tracker'!$E$2:$E$766=$A341)/('Weekly Tracker'!$F$2:$F$766<>""),'Weekly Tracker'!$G$2:$G$766),"") | H341: =IFERROR(LOOKUP(2,1/('Weekly Tracker'!$E$2:$E$766=$A341)/('Weekly Tracker'!$H$2:$H$766<>""),'Weekly Tracker'!$H$2:$H$766),"") | I341: =IF(H341<>"",LOOKUP(2,1/('Weekly Tracker'!$E$2:$E$766=$A341)/('Weekly Tracker'!$H$2:$H$766<>""),'Weekly Tracker'!$I$2:$I$766),"") | J341: =IFERROR(LOOKUP(2,1/('Weekly Tracker'!$E$2:$E$766=$A341)/('Weekly Tracker'!$J$2:$J$766<>""),'Weekly Tracker'!$J$2:$J$766),"") | K341: =IFERROR(LOOKUP(2,1/('Weekly Tracker'!$E$2:$E$766=$A341)/('Weekly Tracker'!$N$2:$N$766<>""),'Weekly Tracker'!$N$2:$N$766),"") | L341: =IFERROR(LOOKUP(2,1/('Weekly Tracker'!$E$2:$E$766=$A341)/('Weekly Tracker'!$O$2:$O$766<>""),'Weekly Tracker'!$O$2:$O$766),"")
A342: Pradhap Ndlf | B342: 917299988483 | F342: =IFERROR(LOOKUP(2,1/('Weekly Tracker'!$E$2:$E$766=$A342)/('Weekly Tracker'!$F$2:$F$766<>""),'Weekly Tracker'!$F$2:$F$766),"") | G342: =IF(F342<>"",LOOKUP(2,1/('Weekly Tracker'!$E$2:$E$766=$A342)/('Weekly Tracker'!$F$2:$F$766<>""),'Weekly Tracker'!$G$2:$G$766),"") | H342: =IFERROR(LOOKUP(2,1/('Weekly Tracker'!$E$2:$E$766=$A342)/('Weekly Tracker'!$H$2:$H$766<>""),'Weekly Tracker'!$H$2:$H$766),"") | I342: =IF(H342<>"",LOOKUP(2,1/('Weekly Tracker'!$E$2:$E$766=$A342)/('Weekly Tracker'!$H$2:$H$766<>""),'Weekly Tracker'!$I$2:$I$766),"") | J342: =IFERROR(LOOKUP(2,1/('Weekly Tracker'!$E$2:$E$766=$A342)/('Weekly Tracker'!$J$2:$J$766<>""),'Weekly Tracker'!$J$2:$J$766),"") | K342: =IFERROR(LOOKUP(2,1/('Weekly Tracker'!$E$2:$E$766=$A342)/('Weekly Tracker'!$N$2:$N$766<>""),'Weekly Tracker'!$N$2:$N$766),"") | L342: =IFERROR(LOOKUP(2,1/('Weekly Tracker'!$E$2:$E$766=$A342)/('Weekly Tracker'!$O$2:$O$766<>""),'Weekly Tracker'!$O$2:$O$766),"")
A343: Kuzhaly Ece | B343: 917598644716 | F343: =IFERROR(LOOKUP(2,1/('Weekly Tracker'!$E$2:$E$766=$A343)/('Weekly Tracker'!$F$2:$F$766<>""),'Weekly Tracker'!$F$2:$F$766),"") | G343: =IF(F343<>"",LOOKUP(2,1/('Weekly Tracker'!$E$2:$E$766=$A343)/('Weekly Tracker'!$F$2:$F$766<>""),'Weekly Tracker'!$G$2:$G$766),"") | H343: =IFERROR(LOOKUP(2,1/('Weekly Tracker'!$E$2:$E$766=$A343)/('Weekly Tracker'!$H$2:$H$766<>""),'Weekly Tracker'!$H$2:$H$766),"") | I343: =IF(H343<>"",LOOKUP(2,1/('Weekly Tracker'!$E$2:$E$766=$A343)/('Weekly Tracker'!$H$2:$H$766<>""),'Weekly Tracker'!$I$2:$I$766),"") | J343: =IFERROR(LOOKUP(2,1/('Weekly Tracker'!$E$2:$E$766=$A343)/('Weekly Tracker'!$J$2:$J$766<>""),'Weekly Tracker'!$J$2:$J$766),"") | K343: =IFERROR(LOOKUP(2,1/('Weekly Tracker'!$E$2:$E$766=$A343)/('Weekly Tracker'!$N$2:$N$766<>""),'Weekly Tracker'!$N$2:$N$766),"") | L343: =IFERROR(LOOKUP(2,1/('Weekly Tracker'!$E$2:$E$766=$A343)/('Weekly Tracker'!$O$2:$O$766<>""),'Weekly Tracker'!$O$2:$O$766),"")
A344: Agalya TCS Junior | B344: 9944223466 | F344: =IFERROR(LOOKUP(2,1/('Weekly Tracker'!$E$2:$E$766=$A344)/('Weekly Tracker'!$F$2:$F$766<>""),'Weekly Tracker'!$F$2:$F$766),"") | G344: =IF(F344<>"",LOOKUP(2,1/('Weekly Tracker'!$E$2:$E$766=$A344)/('Weekly Tracker'!$F$2:$F$766<>""),'Weekly Tracker'!$G$2:$G$766),"") | H344: =IFERROR(LOOKUP(2,1/('Weekly Tracker'!$E$2:$E$766=$A344)/('Weekly Tracker'!$H$2:$H$766<>""),'Weekly Tracker'!$H$2:$H$766),"") | I344: =IF(H344<>"",LOOKUP(2,1/('Weekly Tracker'!$E$2:$E$766=$A344)/('Weekly Tracker'!$H$2:$H$766<>""),'Weekly Tracker'!$I$2:$I$766),"") | J344: =IFERROR(LOOKUP(2,1/('Weekly Tracker'!$E$2:$E$766=$A344)/('Weekly Tracker'!$J$2:$J$766<>""),'Weekly Tracker'!$J$2:$J$766),"") | K344: =IFERROR(LOOKUP(2,1/('Weekly Tracker'!$E$2:$E$766=$A344)/('Weekly Tracker'!$N$2:$N$766<>""),'Weekly Tracker'!$N$2:$N$766),"") | L344: =IFERROR(LOOKUP(2,1/('Weekly Tracker'!$E$2:$E$766=$A344)/('Weekly Tracker'!$O$2:$O$766<>""),'Weekly Tracker'!$O$2:$O$766),"")
... A368: Ag Karthi Vel-frd | B368: 919994265060 | F368: =IFERROR(LOOKUP(2,1/('Weekly Tracker'!$E$2:$E$766=$A368)/('Weekly Tracker'!$F$2:$F$766<>""),'Weekly Tracker'!$F$2:$F$766),"") | G368: =IF(F368<>"",LOOKUP(2,1/('Weekly Tracker'!$E$2:$E$766=$A368)/('Weekly Tracker'!$F$2:$F$766<>""),'Weekly Tracker'!$G$2:$G$766),"") | H368: =IFERROR(LOOKUP(2,1/('Weekly Tracker'!$E$2:$E$766=$A368)/('Weekly Tracker'!$H$2:$H$766<>""),'Weekly Tracker'!$H$2:$H$766),"") | I368: =IF(H368<>"",LOOKUP(2,1/('Weekly Tracker'!$E$2:$E$766=$A368)/('Weekly Tracker'!$H$2:$H$766<>""),'Weekly Tracker'!$I$2:$I$766),"") | J368: =IFERROR(LOOKUP(2,1/('Weekly Tracker'!$E$2:$E$766=$A368)/('Weekly Tracker'!$J$2:$J$766<>""),'Weekly Tracker'!$J$2:$J$766),"") | K368: =IFERROR(LOOKUP(2,1/('Weekly Tracker'!$E$2:$E$766=$A368)/('Weekly Tracker'!$N$2:$N$766<>""),'Weekly Tracker'!$N$2:$N$766),"") | L368: =IFERROR(LOOKUP(2,1/('Weekly Tracker'!$E$2:$E$766=$A368)/('Weekly Tracker'!$O$2:$O$766<>""),'Weekly Tracker'!$O$2:$O$766),"")
A369: Karthi Rpk Scl | B369: 917904755114 | E369: Tamil Nadu, India | F369: =IFERROR(LOOKUP(2,1/('Weekly Tracker'!$E$2:$E$766=$A369)/('Weekly Tracker'!$F$2:$F$766<>""),'Weekly Tracker'!$F$2:$F$766),"") | G369: =IF(F369<>"",LOOKUP(2,1/('Weekly Tracker'!$E$2:$E$766=$A369)/('Weekly Tracker'!$F$2:$F$766<>""),'Weekly Tracker'!$G$2:$G$766),"") | H369: =IFERROR(LOOKUP(2,1/('Weekly Tracker'!$E$2:$E$766=$A369)/('Weekly Tracker'!$H$2:$H$766<>""),'Weekly Tracker'!$H$2:$H$766),"") | I369: =IF(H369<>"",LOOKUP(2,1/('Weekly Tracker'!$E$2:$E$766=$A369)/('Weekly Tracker'!$H$2:$H$766<>""),'Weekly Tracker'!$I$2:$I$766),"") | J369: =IFERROR(LOOKUP(2,1/('Weekly Tracker'!$E$2:$E$766=$A369)/('Weekly Tracker'!$J$2:$J$766<>""),'Weekly Tracker'!$J$2:$J$766),"") | K369: =IFERROR(LOOKUP(2,1/('Weekly Tracker'!$E$2:$E$766=$A369)/('Weekly Tracker'!$N$2:$N$766<>""),'Weekly Tracker'!$N$2:$N$766),"") | L369: =IFERROR(LOOKUP(2,1/('Weekly Tracker'!$E$2:$E$766=$A369)/('Weekly Tracker'!$O$2:$O$766<>""),'Weekly Tracker'!$O$2:$O$766),"")
A370: Mahendran Urja | B370: 916379889927 | E370: Tamil Nadu, India | F370: =IFERROR(LOOKUP(2,1/('Weekly Tracker'!$E$2:$E$766=$A370)/('Weekly Tracker'!$F$2:$F$766<>""),'Weekly Tracker'!$F$2:$F$766),"") | G370: =IF(F370<>"",LOOKUP(2,1/('Weekly Tracker'!$E$2:$E$766=$A370)/('Weekly Tracker'!$F$2:$F$766<>""),'Weekly Tracker'!$G$2:$G$766),"") | H370: =IFERROR(LOOKUP(2,1/('Weekly Tracker'!$E$2:$E$766=$A370)/('Weekly Tracker'!$H$2:$H$766<>""),'Weekly Tracker'!$H$2:$H$766),"") | I370: =IF(H370<>"",LOOKUP(2,1/('Weekly Tracker'!$E$2:$E$766=$A370)/('Weekly Tracker'!$H$2:$H$766<>""),'Weekly Tracker'!$I$2:$I$766),"") | J370: =IFERROR(LOOKUP(2,1/('Weekly Tracker'!$E$2:$E$766=$A370)/('Weekly Tracker'!$J$2:$J$766<>""),'Weekly Tracker'!$J$2:$J$766),"") | K370: =IFERROR(LOOKUP(2,1/('Weekly Tracker'!$E$2:$E$766=$A370)/('Weekly Tracker'!$N$2:$N$766<>""),'Weekly Tracker'!$N$2:$N$766),"") | L370: =IFERROR(LOOKUP(2,1/('Weekly Tracker'!$E$2:$E$766=$A370)/('Weekly Tracker'!$O$2:$O$766<>""),'Weekly Tracker'!$O$2:$O$766),"")
A371: Vinoth G Mech | B371: 919600970080 | F371: =IFERROR(LOOKUP(2,1/('Weekly Tracker'!$E$2:$E$766=$A371)/('Weekly Tracker'!$F$2:$F$766<>""),'Weekly Tracker'!$F$2:$F$766),"") | G371: =IF(F371<>"",LOOKUP(2,1/('Weekly Tracker'!$E$2:$E$766=$A371)/('Weekly Tracker'!$F$2:$F$766<>""),'Weekly Tracker'!$G$2:$G$766),"") | H371: =IFERROR(LOOKUP(2,1/('Weekly Tracker'!$E$2:$E$766=$A371)/('Weekly Tracker'!$H$2:$H$766<>""),'Weekly Tracker'!$H$2:$H$766),"") | I371: =IF(H371<>"",LOOKUP(2,1/('Weekly Tracker'!$E$2:$E$766=$A371)/('Weekly Tracker'!$H$2:$H$766<>""),'Weekly Tracker'!$I$2:$I$766),"") | J371: =IFERROR(LOOKUP(2,1/('Weekly Tracker'!$E$2:$E$766=$A371)/('Weekly Tracker'!$J$2:$J$766<>""),'Weekly Tracker'!$J$2:$J$766),"") | K371: =IFERROR(LOOKUP(2,1/('Weekly Tracker'!$E$2:$E$766=$A371)/('Weekly Tracker'!$N$2:$N$766<>""),'Weekly Tracker'!$N$2:$N$766),"") | L371: =IFERROR(LOOKUP(2,1/('Weekly Tracker'!$E$2:$E$766=$A371)/('Weekly Tracker'!$O$2:$O$766<>""),'Weekly Tracker'!$O$2:$O$766),"")
...

Sheet Read Me
A1: QNET 2026 SALES TRACKER – HOW TO USE
A3: 1. Weekly Tracker: Starting from AUG Week 31, select the Sales Month/Week and then select a Name from the dropdown.
A4: 2. Info: Enter the response in Info. Enter Info_Date when you make the update. The Main sheet will pull the latest non-empty Info response/date for that Name.
A5: 3. Invite: Enter the response in Invite and Invite_Date. The Main sheet will pull the latest non-empty Invite response/date.
A6: 4. Plans: Enter the response in Plan. The Main sheet will pull the latest non-empty Plan response.
A7: 5. Comments & Notes: Enter these against the Name in Weekly Tracker. The latest non-empty value is shown in Main.
A8: 6. New Numbers: Use the New Numbers sheet for new contacts. Enter Name, Number, Connection and Location. Then add the new person as a new row in Main so they become part of the master Name dropdown.
A9: 7. Dashboard: Shows weekly and monthly counts for Info, Invite, Plans and New Numbers. Charts update when you enter tracker data.
A10: 8. Dates: The workbook is designed for August–December 2026, following the provided QNET Sales Month Calendar (Week 31 to Week 52).
A11: 9. Important: Excel formulas update the Main sheet when the workbook recalculates. For a permanent timestamp that never changes, enter the actual update date in Info_Date / Invite_Date rather than using TODAY().

Sheet Dashboard
A1: QNET 2026 SALES DASHBOARD | J1: KPI
J2: Total Contacts | K2: =COUNTA(Main!$A$2:$A$1645)
A3: Weekly Progress | J3: Info Updates | K3: =COUNTIF('Weekly Tracker'!$F$2:$F$2001,"<>")
A4: Week | B4: Start | C4: End | D4: Info | E4: Invite | F4: Plans | G4: New Numbers | H4: Total Activity | J4: Invite Updates | K4: =COUNTIF('Weekly Tracker'!$H$2:$H$2001,"<>")
A5: 31 | B5: 46234 | C5: 46240 | D5: =COUNTIFS('Weekly Tracker'!$D$2:$D$766,$A5,'Weekly Tracker'!$F$2:$F$766,"<>") | E5: =COUNTIFS('Weekly Tracker'!$D$2:$D$766,$A5,'Weekly Tracker'!$H$2:$H$766,"<>") | F5: =COUNTIFS('Weekly Tracker'!$D$2:$D$766,$A5,'Weekly Tracker'!$J$2:$J$766,"<>") | G5: =COUNTIFS('Weekly Tracker'!$D$2:$D$766,$A5,'Weekly Tracker'!$K$2:$K$766,"<>") | H5: =SUM(D5:G5) | J5: Plan Updates | K5: =COUNTIF('Weekly Tracker'!$J$2:$J$2001,"<>")
A6: 32 | B6: 46241 | C6: 46247 | D6: =COUNTIFS('Weekly Tracker'!$D$2:$D$766,$A6,'Weekly Tracker'!$F$2:$F$766,"<>") | E6: =COUNTIFS('Weekly Tracker'!$D$2:$D$766,$A6,'Weekly Tracker'!$H$2:$H$766,"<>") | F6: =COUNTIFS('Weekly Tracker'!$D$2:$D$766,$A6,'Weekly Tracker'!$J$2:$J$766,"<>") | G6: =COUNTIFS('Weekly Tracker'!$D$2:$D$766,$A6,'Weekly Tracker'!$K$2:$K$766,"<>") | H6: =SUM(D6:G6) | J6: New Numbers | K6: =COUNTIF('New Numbers'!$D$2:$D$501,"<>")
A7: 33 | B7: 46248 | C7: 46254 | D7: =COUNTIFS('Weekly Tracker'!$D$2:$D$766,$A7,'Weekly Tracker'!$F$2:$F$766,"<>") | E7: =COUNTIFS('Weekly Tracker'!$D$2:$D$766,$A7,'Weekly Tracker'!$H$2:$H$766,"<>") | F7: =COUNTIFS('Weekly Tracker'!$D$2:$D$766,$A7,'Weekly Tracker'!$J$2:$J$766,"<>") | G7: =COUNTIFS('Weekly Tracker'!$D$2:$D$766,$A7,'Weekly Tracker'!$K$2:$K$766,"<>") | H7: =SUM(D7:G7)
A8: 34 | B8: 46255 | C8: 46261 | D8: =COUNTIFS('Weekly Tracker'!$D$2:$D$766,$A8,'Weekly Tracker'!$F$2:$F$766,"<>") | E8: =COUNTIFS('Weekly Tracker'!$D$2:$D$766,$A8,'Weekly Tracker'!$H$2:$H$766,"<>") | F8: =COUNTIFS('Weekly Tracker'!$D$2:$D$766,$A8,'Weekly Tracker'!$J$2:$J$766,"<>") | G8: =COUNTIFS('Weekly Tracker'!$D$2:$D$766,$A8,'Weekly Tracker'!$K$2:$K$766,"<>") | H8: =SUM(D8:G8)
A9: 35 | B9: 46262 | C9: 46268 | D9: =COUNTIFS('Weekly Tracker'!$D$2:$D$766,$A9,'Weekly Tracker'!$F$2:$F$766,"<>") | E9: =COUNTIFS('Weekly Tracker'!$D$2:$D$766,$A9,'Weekly Tracker'!$H$2:$H$766,"<>") | F9: =COUNTIFS('Weekly Tracker'!$D$2:$D$766,$A9,'Weekly Tracker'!$J$2:$J$766,"<>") | G9: =COUNTIFS('Weekly Tracker'!$D$2:$D$766,$A9,'Weekly Tracker'!$K$2:$K$766,"<>") | H9: =SUM(D9:G9)
A10: 36 | B10: 46269 | C10: 46275 | D10: =COUNTIFS('Weekly Tracker'!$D$2:$D$766,$A10,'Weekly Tracker'!$F$2:$F$766,"<>") | E10: =COUNTIFS('Weekly Tracker'!$D$2:$D$766,$A10,'Weekly Tracker'!$H$2:$H$766,"<>") | F10: =COUNTIFS('Weekly Tracker'!$D$2:$D$766,$A10,'Weekly Tracker'!$J$2:$J$766,"<>") | G10: =COUNTIFS('Weekly Tracker'!$D$2:$D$766,$A10,'Weekly Tracker'!$K$2:$K$766,"<>") | H10: =SUM(D10:G10)
A11: 37 | B11: 46276 | C11: 46282 | D11: =COUNTIFS('Weekly Tracker'!$D$2:$D$766,$A11,'Weekly Tracker'!$F$2:$F$766,"<>") | E11: =COUNTIFS('Weekly Tracker'!$D$2:$D$766,$A11,'Weekly Tracker'!$H$2:$H$766,"<>") | F11: =COUNTIFS('Weekly Tracker'!$D$2:$D$766,$A11,'Weekly Tracker'!$J$2:$J$766,"<>") | G11: =COUNTIFS('Weekly Tracker'!$D$2:$D$766,$A11,'Weekly Tracker'!$K$2:$K$766,"<>") | H11: =SUM(D11:G11)
A12: 38 | B12: 46283 | C12: 46289 | D12: =COUNTIFS('Weekly Tracker'!$D$2:$D$766,$A12,'Weekly Tracker'!$F$2:$F$766,"<>") | E12: =COUNTIFS('Weekly Tracker'!$D$2:$D$766,$A12,'Weekly Tracker'!$H$2:$H$766,"<>") | F12: =COUNTIFS('Weekly Tracker'!$D$2:$D$766,$A12,'Weekly Tracker'!$J$2:$J$766,"<>") | G12: =COUNTIFS('Weekly Tracker'!$D$2:$D$766,$A12,'Weekly Tracker'!$K$2:$K$766,"<>") | H12: =SUM(D12:G12)
A13: 39 | B13: 46290 | C13: 46296 | D13: =COUNTIFS('Weekly Tracker'!$D$2:$D$766,$A13,'Weekly Tracker'!$F$2:$F$766,"<>") | E13: =COUNTIFS('Weekly Tracker'!$D$2:$D$766,$A13,'Weekly Tracker'!$H$2:$H$766,"<>") | F13: =COUNTIFS('Weekly Tracker'!$D$2:$D$766,$A13,'Weekly Tracker'!$J$2:$J$766,"<>") | G13: =COUNTIFS('Weekly Tracker'!$D$2:$D$766,$A13,'Weekly Tracker'!$K$2:$K$766,"<>") | H13: =SUM(D13:G13)
A14: 40 | B14: 46297 | C14: 46303 | D14: =COUNTIFS('Weekly Tracker'!$D$2:$D$766,$A14,'Weekly Tracker'!$F$2:$F$766,"<>") | E14: =COUNTIFS('Weekly Tracker'!$D$2:$D$766,$A14,'Weekly Tracker'!$H$2:$H$766,"<>") | F14: =COUNTIFS('Weekly Tracker'!$D$2:$D$766,$A14,'Weekly Tracker'!$J$2:$J$766,"<>") | G14: =COUNTIFS('Weekly Tracker'!$D$2:$D$766,$A14,'Weekly Tracker'!$K$2:$K$766,"<>") | H14: =SUM(D14:G14)
A15: 41 | B15: 46304 | C15: 46310 | D15: =COUNTIFS('Weekly Tracker'!$D$2:$D$766,$A15,'Weekly Tracker'!$F$2:$F$766,"<>") | E15: =COUNTIFS('Weekly Tracker'!$D$2:$D$766,$A15,'Weekly Tracker'!$H$2:$H$766,"<>") | F15: =COUNTIFS('Weekly Tracker'!$D$2:$D$766,$A15,'Weekly Tracker'!$J$2:$J$766,"<>") | G15: =COUNTIFS('Weekly Tracker'!$D$2:$D$766,$A15,'Weekly Tracker'!$K$2:$K$766,"<>") | H15: =SUM(D15:G15)
A16: 42 | B16: 46311 | C16: 46317 | D16: =COUNTIFS('Weekly Tracker'!$D$2:$D$766,$A16,'Weekly Tracker'!$F$2:$F$766,"<>") | E16: =COUNTIFS('Weekly Tracker'!$D$2:$D$766,$A16,'Weekly Tracker'!$H$2:$H$766,"<>") | F16: =COUNTIFS('Weekly Tracker'!$D$2:$D$766,$A16,'Weekly Tracker'!$J$2:$J$766,"<>") | G16: =COUNTIFS('Weekly Tracker'!$D$2:$D$766,$A16,'Weekly Tracker'!$K$2:$K$766,"<>") | H16: =SUM(D16:G16)
A17: 43 | B17: 46318 | C17: 46324 | D17: =COUNTIFS('Weekly Tracker'!$D$2:$D$766,$A17,'Weekly Tracker'!$F$2:$F$766,"<>") | E17: =COUNTIFS('Weekly Tracker'!$D$2:$D$766,$A17,'Weekly Tracker'!$H$2:$H$766,"<>") | F17: =COUNTIFS('Weekly Tracker'!$D$2:$D$766,$A17,'Weekly Tracker'!$J$2:$J$766,"<>") | G17: =COUNTIFS('Weekly Tracker'!$D$2:$D$766,$A17,'Weekly Tracker'!$K$2:$K$766,"<>") | H17: =SUM(D17:G17)
A18: 44 | B18: 46325 | C18: 46331 | D18: =COUNTIFS('Weekly Tracker'!$D$2:$D$766,$A18,'Weekly Tracker'!$F$2:$F$766,"<>") | E18: =COUNTIFS('Weekly Tracker'!$D$2:$D$766,$A18,'Weekly Tracker'!$H$2:$H$766,"<>") | F18: =COUNTIFS('Weekly Tracker'!$D$2:$D$766,$A18,'Weekly Tracker'!$J$2:$J$766,"<>") | G18: =COUNTIFS('Weekly Tracker'!$D$2:$D$766,$A18,'Weekly Tracker'!$K$2:$K$766,"<>") | H18: =SUM(D18:G18)
... A26: 52 | B26: 46381 | C26: 46387 | D26: =COUNTIFS('Weekly Tracker'!$D$2:$D$766,$A26,'Weekly Tracker'!$F$2:$F$766,"<>") | E26: =COUNTIFS('Weekly Tracker'!$D$2:$D$766,$A26,'Weekly Tracker'!$H$2:$H$766,"<>") | F26: =COUNTIFS('Weekly Tracker'!$D$2:$D$766,$A26,'Weekly Tracker'!$J$2:$J$766,"<>") | G26: =COUNTIFS('Weekly Tracker'!$D$2:$D$766,$A26,'Weekly Tracker'!$K$2:$K$766,"<>") | H26: =SUM(D26:G26)
A29: Monthly Progress
A30: Month | B30: Info | C30: Invite | D30: Plans | E30: New Numbers | F30: Total Activity
A31: AUG | B31: =COUNTIFS('Weekly Tracker'!$C$2:$C$766,"AUG",'Weekly Tracker'!$F$2:$F$766,"<>") | C31: =COUNTIFS('Weekly Tracker'!$C$2:$C$766,"AUG",'Weekly Tracker'!$H$2:$H$766,"<>") | D31: =COUNTIFS('Weekly Tracker'!$C$2:$C$766,"AUG",'Weekly Tracker'!$J$2:$J$766,"<>") | E31: =COUNTIFS('Weekly Tracker'!$C$2:$C$766,"AUG",'Weekly Tracker'!$K$2:$K$766,"<>") | F31: =SUM(B31:E31)
A32: SEP | B32: =COUNTIFS('Weekly Tracker'!$C$2:$C$766,"SEP",'Weekly Tracker'!$F$2:$F$766,"<>") | C32: =COUNTIFS('Weekly Tracker'!$C$2:$C$766,"SEP",'Weekly Tracker'!$H$2:$H$766,"<>") | D32: =COUNTIFS('Weekly Tracker'!$C$2:$C$766,"SEP",'Weekly Tracker'!$J$2:$J$766,"<>") | E32: =COUNTIFS('Weekly Tracker'!$C$2:$C$766,"SEP",'Weekly Tracker'!$K$2:$K$766,"<>") | F32: =SUM(B32:E32)
A33: OCT | B33: =COUNTIFS('Weekly Tracker'!$C$2:$C$766,"OCT",'Weekly Tracker'!$F$2:$F$766,"<>") | C33: =COUNTIFS('Weekly Tracker'!$C$2:$C$766,"OCT",'Weekly Tracker'!$H$2:$H$766,"<>") | D33: =COUNTIFS('Weekly Tracker'!$C$2:$C$766,"OCT",'Weekly Tracker'!$J$2:$J$766,"<>") | E33: =COUNTIFS('Weekly Tracker'!$C$2:$C$766,"OCT",'Weekly Tracker'!$K$2:$K$766,"<>") | F33: =SUM(B33:E33)
A34: NOV | B34: =COUNTIFS('Weekly Tracker'!$C$2:$C$766,"NOV",'Weekly Tracker'!$F$2:$F$766,"<>") | C34: =COUNTIFS('Weekly Tracker'!$C$2:$C$766,"NOV",'Weekly Tracker'!$H$2:$H$766,"<>") | D34: =COUNTIFS('Weekly Tracker'!$C$2:$C$766,"NOV",'Weekly Tracker'!$J$2:$J$766,"<>") | E34: =COUNTIFS('Weekly Tracker'!$C$2:$C$766,"NOV",'Weekly Tracker'!$K$2:$K$766,"<>") | F34: =SUM(B34:E34)
A35: DEC | B35: =COUNTIFS('Weekly Tracker'!$C$2:$C$766,"DEC",'Weekly Tracker'!$F$2:$F$766,"<>") | C35: =COUNTIFS('Weekly Tracker'!$C$2:$C$766,"DEC",'Weekly Tracker'!$H$2:$H$766,"<>") | D35: =COUNTIFS('Weekly Tracker'!$C$2:$C$766,"DEC",'Weekly Tracker'!$J$2:$J$766,"<>") | E35: =COUNTIFS('Weekly Tracker'!$C$2:$C$766,"DEC",'Weekly Tracker'!$K$2:$K$766,"<>") | F35: =SUM(B35:E35)

Sheet Lists
A1: Name List | B1: Zone List
A2: Samsung Helpline | B2: Warm
A3: Ragul Urja | B3: HOT
A4: Rajesh ramadoss Urja | B4: Cold
A5: Rajesh Past Urja
A6: Ragul Hit Urja
A7: Rajesh FB
A8: Rakesh Urja
A9: Vinoth Mech
A10: Mani Kandan FB
A11: Mani VJ FB
A12: Niranjan Urja
A13: Anbu Urja
A14: Vinoth Kumar Mech
A15: Manikandan FB
A16: Urjanet
... A1645: Ananth Homebeside

Sheet New Numbers
A1: Sales Month | B1: Week No | C1: Date Added | D1: Name | E1: Contact Number | F1: Connection | G1: Location | H1: Comments | I1: Notes | J1: Added to Main?
J2: No
J3: No
J4: No
J5: No
J6: No
J7: No
J8: No
J9: No
J10: No
J11: No
J12: No
J13: No
... J501: No

Sheet Weekly Tracker
A1: Date | B1: Day | C1: Sales Month | D1: Week No | E1: Name | F1: Info | G1: Info_Date | H1: Invite | I1: Invite_Date | J1: Plan | K1: New Number | L1: New Connection | M1: New Location | N1: Comments | O1: Notes | Q1: DAILY TRACKER
A2: 46235 | B2: Saturday | C2: AUG | D2: 31 | Q2: 01-Aug-2026 to 31-Dec-2026
A3: 46235 | B3: Saturday | C3: AUG | D3: 31 | Q3: Every calendar day has exactly 5 rows. Select a Name from the dropdown and enter your daily activity.
A4: 46235 | B4: Saturday | C4: AUG | D4: 31
A5: 46235 | B5: Saturday | C5: AUG | D5: 31
A6: 46235 | B6: Saturday | C6: AUG | D6: 31
A7: 46236 | B7: Sunday | C7: AUG | D7: 31
A8: 46236 | B8: Sunday | C8: AUG | D8: 31
A9: 46236 | B9: Sunday | C9: AUG | D9: 31
A10: 46236 | B10: Sunday | C10: AUG | D10: 31
A11: 46236 | B11: Sunday | C11: AUG | D11: 31
A12: 46237 | B12: Monday | C12: AUG | D12: 31
A13: 46237 | B13: Monday | C13: AUG | D13: 31
A14: 46237 | B14: Monday | C14: AUG | D14: 31
A15: 46237 | B15: Monday | C15: AUG | D15: 31
... A766: 46387 | B766: Thursday | C766: DEC | D766: 52
